Workbook
Name _Toc205793815: '0 - Summary'!#REF!
Name _Toc205793816: '0 - Summary'!#REF!
Name _Toc205793817: '0 - Summary'!#REF!

Sheet 0 - Summary
A1: ŞIRKƏT ADI : "İNDUSTRİAL SERVİCES CONSTRUCTİON GROUP" MMC
A2: İŞLƏRİN HƏCMİ VƏ QİYMƏT CƏDVƏLİ
A4: ÜMUMİ XÜLASƏ
A7: Ümumi xülasə | C7: Məbləğ
C8: AZN
A9: I. Ölçülmüş işlər Beton konstruksiya işləri (BOQ-Measured Works) | C9: ='1 - Direct_DK_BoQ'!L9 -> 997821.08
A10: II. Ölçülmüş işlər Memarlıq işləri (BOQ-Measured Works) | C10: ='2 - Direct_MH_BoQ'!L9 -> 178251.24
A11: III. İlkin və dolayı xərclər (Contractor's Preliminaries) | C11: ='3 - Indirect'!F40 -> 1609500
A12: IV. Üstəlik xərclər (Contractor's Overhead) | C12: ='4 - Overhead'!F20 -> 965400 | G12: =SUM(C11:C12)+I18 -> 2574900
A13: Şirkətin mənfəəti, % (Contractor's Gross Profit Margin, (%) | C13: =(C11+C12+C9+C10)*B13 -> 0 | G13: ='1 - Direct_DK_BoQ'!K6 -> 997821.08
A14: Yekun Muzd | B14: (A) | C14: =SUM(C9:C13) -> 3750972.3 | G14: =SUM(G12:G13) -> 3572721.1
A15: ƏDV (18 % x A) | B15: (B) | C15: =C14*0.18 -> 675175.02 | G15: =G14/G13 -> 3.5805228
A16: Yekun Muzd ƏDV ilə | B16: (C) | C16: =C14+C15 -> 4426147.3
G17: =C13 -> 0 | H17: ='1 - Direct_DK_BoQ'!J6 -> 0 | I17: ='1 - Direct_DK_BoQ'!K6 -> 997821.08 | J17: =SUM(H17:I17) -> 997821.08
H18: =$G$17*H17/$J$17 -> 0 | I18: =$G$17*I17/$J$17 -> 0
A19: Qeyd : Qeyd edilən bölmələri dəyərləndirən zaman "daxildir" praktikasından istifadə etmək olmaz, yəni bütün bəndlər balanslaşdırılmış şəkildə qiymətləndirilməlidir ! | H19: =SUM(H17:H18)/H17 -> #DIV/0!

Sheet 1 - Direct_DK_BoQ
B1: I HİSSƏ: ÖLÇÜLMÜŞ İŞLƏR / MEASURED WORKS
B2: Bənd | E2: Təsviri | F2: Vahid | G2: Miqdar | H2: Açıqlama | I2: Link vəya şəkil | J2: Müqavilə məbləği
J3: Vahid material qiyməti | K3: Vahid işçilik qiyməti | L3: Cəmi məbləğ
J4: AZN
B5: 1 | E5: Bu bölmədə əsas işlərin material və işçilik xərcləri orta bazar qiymətləri əsasında, balanslaşdırılmış şəkildə dəyərləndirilməlidir. Qiymətləndirmə zamanı material itkisi, sərfiyyat normaları və əmsallar, işlə bağlı tələb olunan köməkçi materiallar, materialların daşınması eləcə də gömrükləmə xərcləri nəzərə alınmalıdır. Bu işlərə dair üstəlik və dolayı xərclər, şirkətin mənfəəti vahid qiymətlərə daxil edilməməlidir və qiymət cədvəlinin I ci və II hissələrində öz əksini tapmalıdır. Burada qeyd edilmiş miqdarlar indikativ xarakter daşıyır. Həcmlərin hesablanmasında Sifarişçi tərəfindən təqdim edilən İşlərin Təsvirinə və Texniki Sənədlərə istinad edilməli və aşağıdakılarla məhdudlaşmayaraq İşlərə aid bütün detallar nəzərə alınmalıdır.
E6: Bakı şəhəri, Abşeron rayonu, Bilgəh qəsəbəsi, Zəfəran savxozu ərazisində yerləşən Fərdi yaşayış evi Əsas Bina və İtlər evində Memari işlər | J6: =SUMPRODUCT(J11:J67,$G$11:$G$67) -> 0 | K6: =SUMPRODUCT(K11:K67,$G$11:$G$67) -> 997821.08 | L6: =L7+#REF! -> #REF!
E7: Bakı şəhəri, Abşeron rayonu, Bilgəh qəsəbəsi, Zəfəran savxozu ərazisində yerləşən Fərdi yaşayış evi (Əsas Bina) Memarlıq və İnteryer işləri | L7: =L10+#REF!+#REF!+#REF!+#REF! -> #REF!
B8: 1 | E8: Bu bölmədə əsas işlərin material və işçilik xərcləri orta bazar qiymətləri əsasında, balanslaşdırılmış şəkildə dəyərləndirilməlidir. Qiymətləndirmə zamanı material itkisi, sərfiyyat normaları və əmsallar, işlə bağlı tələb olunan köməkçi materiallar, materialların daşınması eləcə də gömrükləmə xərcləri nəzərə alınmalıdır. Bu işlərə dair üstəlik və dolayı xərclər, şirkətin mənfəəti vahid qiymətlərə daxil edilməməlidir və qiymət cədvəlinin I ci və II hissələrində öz əksini tapmalıdır. Burada qeyd edilmiş miqdarlar indikativ xarakter daşıyır. Həcmlərin hesablanmasında Sifarişçi tərəfindən təqdim edilən İşlərin Təsvirinə və Texniki Sənədlərə istinad edilməli və aşağıdakılarla məhdudlaşmayaraq İşlərə aid bütün detallar nəzərə alınmalıdır.
E9: Ələt Azad İqtisadi Zonasında tikilməsi nəzərdə tutulan su anbarları, içməli və yağış suyu xətlərində Dəmir beton işləri | L9: =SUM(L10,L13,L16,L19,L25,L62) -> 997821.08
B10: 1 | C10: 1 | D10: 0 | E10: Qazıntı | L10: =SUM(L11:L12) -> 186615
B11: 1 | C11: 1 | D11: 1 | E11: Bünövrə oturma səviyyəsinə qədər səviyyələrin endirilməsi üçün qazıntı və qazıntı başa çatdıqdan sonra mexaniki üsulla sıxlaşdırma | F11: m3 | G11: 15455 | H11: (Yalnız işçilik qiymətləndiriləcəkdir) | K11: 8 | L11: =(J11+K11)*G11 -> 123640
B12: 1 | C12: 1 | D12: 2 | E12: Qazılmış torpağın utilizasiyası (daşınması) | F12: m3 | G12: 12595 | H12: (Yalnız işçilik qiymətləndiriləcəkdir) | K12: 5 | L12: =(J12+K12)*G12 -> 62975
B13: 1 | C13: 2 | D13: 0 | E13: Dolgu işləri | L13: =SUM(L14:L15) -> 7506
B14: 1 | C14: 2 | D14: 1 | E14: Spesifikasiyaya uyğun olaraq xırdalanmış çınqıl və ya qırmadaşdan istifadə etməklə doldurma və mexaniki üsulla sıxlaşdırma (h:100 mm) | F14: m3 | G14: 466 | H14: (Yalnız işçilik qiymətləndiriləcəkdir) | K14: 3.5 | L14: =(J14+K14)*G14 -> 1631
B15: 1 | C15: 2 | D15: 2 | E15: Əvvəlcədən qazılmış torpaqla geri doldurma | F15: m3 | G15: 2350 | H15: (Yalnız işçilik qiymətləndiriləcəkdir) | K15: 2.5 | L15: =(J15+K15)*G15 -> 5875
B16: 1 | C16: 3 | D16: 0 | E16: Qoruyucu qat | L16: =SUM(L17:L18) -> 11696
B17: 1 | C17: 3 | D17: 1 | E17: Beton altına polietilen salafan təbəqənin sərilməsi (Polietilen plyonka) | F17: m2 | G17: 4688 | H17: (Yalnız işçilik qiymətləndiriləcəkdir) | K17: 2 | L17: =(J17+K17)*G17 -> 9376
B18: 1 | C18: 3 | D18: 2 | E18: Hazırlıq qatı beton B7.5, bünövrə plitələri üçün hazırlıq qatı (h:100 mm) (Beton B7.5) | F18: m3 | G18: 464 | H18: (Yalnız işçilik qiymətləndiriləcəkdir) | K18: 5 | L18: =(J18+K18)*G18 -> 2320
B19: 1 | C19: 4 | D19: 0 | E19: İzolyasiya işləri | L19: =SUM(L20:L24) -> 81488.8
B20: 1 | C20: 4 | D20: 1 | E20: Bitumla yapışdırılmış 2qat ruberoidlə üfüqi hidroizolyasiya edilməsi | F20: m2 | G20: 4988 | H20: (Yalnız işçilik qiymətləndiriləcəkdir) | K20: 9 | L20: =(J20+K20)*G20 -> 44892
B21: 1 | C21: 4 | D21: 2 | E21: Qoruyucu-hamarlayıcı qatın sement məhlulundan düzəldilməsi 30mm | F21: m3 | G21: 229 | H21: (Yalnız işçilik qiymətləndiriləcəkdir) | K21: 7 | L21: =(J21+K21)*G21 -> 1603
B22: 1 | C22: 4 | D22: 3 | E22: Bitumla yapışdırılmış 2qat ruberoidlə üfüqi hidroizolyasiya edilməsi | F22: m2 | G22: 1066 | H22: (Yalnız işçilik qiymətləndiriləcəkdir) | K22: 9 | L22: =(J22+K22)*G22 -> 9594
B23: 1 | C23: 4 | D23: 4 | E23: XPS 50mm | F23: m2 | G23: 1411.1 | H23: (Yalnız işçilik qiymətləndiriləcəkdir) | K23: 4 | L23: =(J23+K23)*G23 -> 5644.4
B24: 1 | C24: 4 | D24: 5 | E24: Drenaj lövhəsinin (drain board) quraşdırılması | F24: m2 | G24: 1411.1 | H24: (Yalnız işçilik qiymətləndiriləcəkdir) | K24: 14 | L24: =(J24+K24)*G24 -> 19755.4
B25: 1 | C25: 5 | D25: 0 | E25: Dəmir beton işləri | L25: =SUM(L26,L32,L39,L45,L52,L57) -> 707452.27
B26: 1 | C26: 5 | D26: 1 | E26: Tava bünövrə | L26: =SUM(L27:L31) -> 219055.54
B27: 1 | C27: 5 | D27: 1 | E27: Sulfata davamlı beton B25 W8 | F27: m3 | G27: 1842.08 | H27: (Yalnız işçilik qiymətləndiriləcəkdir) | K27: 70 | L27: =(J27+K27)*G27 -> 128945.6
B28: 1 | C28: 5 | D28: 2 | E28: Qəlib işləri | F28: m2 | G28: 212 | H28: (Yalnız işçilik qiymətləndiriləcəkdir) | K28: 12 | L28: =(J28+K28)*G28 -> 2544
B29: 1 | C29: 5 | D29: 3 | E29: Armatur, sinif A500C Ø10 mm | F29: ton | G29: 0.192504 | H29: (Yalnız işçilik qiymətləndiriləcəkdir) | K29: 650 | L29: =(J29+K29)*G29 -> 125.1276
B30: 1 | C30: 5 | D30: 4 | E30: Armatur, sinif A500C Ø14 mm | F30: ton | G30: 125.9566 | H30: (Yalnız işçilik qiymətləndiriləcəkdir) | K30: 650 | L30: =(J30+K30)*G30 -> 81871.787
B31: 1 | C31: 5 | D31: 5 | E31: Armatur, sinif A-I (A240) Ø8 mm | F31: ton | G31: 8.5677372 | H31: (Yalnız işçilik qiymətləndiriləcəkdir) | K31: 650 | L31: =(J31+K31)*G31 -> 5569.0292
B32: 1 | C32: 6 | D32: 2 | E32: Sütunlar | L32: =SUM(L33:L38) -> 23547.615
B33: 1 | C33: =$C$32 -> 6 | D33: 1 | E33: Sulfata davamlı beton B25 W8 | F33: m3 | G33: 107.72 | H33: (Yalnız işçilik qiymətləndiriləcəkdir) | K33: 70 | L33: =(J33+K33)*G33 -> 7540.4
B34: 1 | C34: =$C$32 -> 6 | D34: 2 | E34: Qəlib işləri | F34: m2 | G34: 418.56 | H34: (Yalnız işçilik qiymətləndiriləcəkdir) | K34: 12 | L34: =(J34+K34)*G34 -> 5022.72
B35: 1 | C35: =$C$32 -> 6 | D35: 3 | E35: Armatur, sinif A500C Ø14 mm | F35: ton | G35: 3.4655104 | H35: (Yalnız işçilik qiymətləndiriləcəkdir) | K35: 650 | L35: =(J35+K35)*G35 -> 2252.5818
B36: 1 | C36: =$C$32 -> 6 | D36: 4 | E36: Armatur, sinif A500C Ø16 mm | F36: ton | G36: 7.188352 | H36: (Yalnız işçilik qiymətləndiriləcəkdir) | K36: 650 | L36: =(J36+K36)*G36 -> 4672.4288
B37: 1 | C37: =$C$32 -> 6 | D37: 5 | E37: Armatur, sinif A500C Ø18 mm | F37: ton | G37: 3.0002928 | H37: (Yalnız işçilik qiymətləndiriləcəkdir) | K37: 650 | L37: =(J37+K37)*G37 -> 1950.1903
B38: 1 | C38: =$C$32 -> 6 | D38: 6 | E38: Armatur, sinif A-I (A240) Ø8 mm | F38: ton | G38: 3.2450672 | H38: (Yalnız işçilik qiymətləndiriləcəkdir) | K38: 650 | L38: =(J38+K38)*G38 -> 2109.2937
B39: 1 | C39: 7 | D39: 3 | E39: Pərdə divarlar | L39: =SUM(L40:L44) -> 263602.79
B40: 1 | C40: =$C$39 -> 7 | D40: 1 | E40: Sulfata davamlı beton B25 W8 | F40: m3 | G40: 1035 | H40: (Yalnız işçilik qiymətləndiriləcəkdir) | K40: 70 | L40: =(J40+K40)*G40 -> 72450
B41: 1 | C41: =$C$39 -> 7 | D41: =D40+1 -> 2 | E41: Qəlib işləri | F41: m2 | G41: 6703.36 | H41: (Yalnız işçilik qiymətləndiriləcəkdir) | K41: 20 | L41: =(J41+K41)*G41 -> 134067.2
B42: 1 | C42: =$C$39 -> 7 | D42: =D41+1 -> 3 | E42: Armatur, sinif A500C Ø12 mm | F42: ton | G42: 36.960295 | H42: (Yalnız işçilik qiymətləndiriləcəkdir) | K42: 650 | L42: =(J42+K42)*G42 -> 24024.192
B43: 1 | C43: =$C$39 -> 7 | D43: =D42+1 -> 4 | E43: Armatur, sinif A500C Ø14 mm | F43: ton | G43: 47.819983 | H43: (Yalnız işçilik qiymətləndiriləcəkdir) | K43: 650 | L43: =(J43+K43)*G43 -> 31082.989
B44: 1 | C44: =$C$39 -> 7 | D44: =D43+1 -> 5 | E44: Armatur, sinif A-I (A240) Ø8 mm | F44: ton | G44: 3.043712 | H44: (Yalnız işçilik qiymətləndiriləcəkdir) | K44: 650 | L44: =(J44+K44)*G44 -> 1978.4128
B45: 1 | C45: 8 | D45: 4 | E45: Rigerlər | L45: =SUM(L46:L51) -> 43600.977
B46: 1 | C46: =$C$45 -> 8 | D46: 1 | E46: Beton B25 | F46: m3 | G46: 208.6 | H46: (Yalnız işçilik qiymətləndiriləcəkdir) | K46: 70 | L46: =(J46+K46)*G46 -> 14602
B47: 1 | C47: =$C$45 -> 8 | D47: =D46+1 -> 2 | E47: Qəlib işləri | F47: m2 | G47: 649.332 | H47: (Yalnız işçilik qiymətləndiriləcəkdir) | K47: 12 | L47: =(J47+K47)*G47 -> 7791.984
B48: 1 | C48: =$C$45 -> 8 | D48: =D47+1 -> 3 | E48: Armatur, sinif A500C Ø16 mm | F48: ton | G48: 6.715632 | H48: (Yalnız işçilik qiymətləndiriləcəkdir) | K48: 650 | L48: =(J48+K48)*G48 -> 4365.1608
B49: 1 | C49: =$C$45 -> 8 | D49: =D48+1 -> 4 | E49: Armatur, sinif A500C Ø20 mm | F49: ton | G49: 18.757114 | H49: (Yalnız işçilik qiymətləndiriləcəkdir) | K49: 650 | L49: =(J49+K49)*G49 -> 12192.124
B50: 1 | C50: =$C$45 -> 8 | D50: =D49+1 -> 5 | E50: Armatur, sinif A500C Ø25 mm | F50: ton | G50: 0.6066348 | H50: (Yalnız işçilik qiymətləndiriləcəkdir) | K50: 650 | L50: =(J50+K50)*G50 -> 394.31262
B51: 1 | C51: =$C$45 -> 8 | D51: =D50+1 -> 6 | E51: Armatur, sinif A-I (A240) Ø8 mm | F51: ton | G51: 6.5467616 | H51: (Yalnız işçilik qiymətləndiriləcəkdir) | K51: 650 | L51: =(J51+K51)*G51 -> 4255.395
B52: 1 | C52: 9 | D52: 5 | E52: Pilləkan | L52: =SUM(L53:L56) -> 675.10153
B53: 1 | C53: 9 | D53: 1 | E53: Beton B25 | F53: m3 | G53: 3.72 | H53: (Yalnız işçilik qiymətləndiriləcəkdir) | K53: 70 | L53: =(J53+K53)*G53 -> 260.4
B54: 1 | C54: 9 | D54: 2 | E54: Qəlib işləri | F54: m2 | G54: 19.94 | H54: (Yalnız işçilik qiymətləndiriləcəkdir) | K54: 12 | L54: =(J54+K54)*G54 -> 239.28
B55: 1 | C55: 9 | D55: 3 | E55: Armatur, sinif A500C Ø10 mm | F55: ton | G55: 0.211014 | H55: (Yalnız işçilik qiymətləndiriləcəkdir) | K55: 650 | L55: =(J55+K55)*G55 -> 137.1591
B56: 1 | C56: 9 | D56: 4 | E56: Armatur, sinif A-I (A240) Ø8 mm | F56: ton | G56: 0.05886528 | H56: (Yalnız işçilik qiymətləndiriləcəkdir) | K56: 650 | L56: =(J56+K56)*G56 -> 38.262432
B57: 1 | C57: 10 | D57: 6 | E57: Örtük döşəmə (-0.15 msl, +4.30 msl, +5.70 msl) | L57: =SUM(L58:L61) -> 156970.24
B58: 1 | C58: 10 | D58: 1 | E58: Beton B25 | F58: m3 | G58: 751.4 | H58: (Yalnız işçilik qiymətləndiriləcəkdir) | K58: 70 | L58: =(J58+K58)*G58 -> 52598
B59: 1 | C59: 10 | D59: 2 | E59: Qəlib işləri | F59: m2 | G59: 4101 | H59: (Yalnız işçilik qiymətləndiriləcəkdir) | K59: 12 | L59: =(J59+K59)*G59 -> 49212
B60: 1 | C60: 10 | D60: 3 | E60: Armatur, sinif A500C Ø12 mm | F60: ton | G60: 81.058051 | H60: (Yalnız işçilik qiymətləndiriləcəkdir) | K60: 650 | L60: =(J60+K60)*G60 -> 52687.733
B61: 1 | C61: 10 | D61: 4 | E61: Armatur, sinif A-I (A240) Ø8 mm | F61: ton | G61: 3.8038522 | H61: (Yalnız işçilik qiymətləndiriləcəkdir) | K61: 650 | L61: =(J61+K61)*G61 -> 2472.504
B62: 1 | C62: 6 | D62: 0 | E62: Metal konstruksiyalar | L62: =SUM(L63:L67) -> 3063.01
B63: 1 | C63: 6 | D63: 1 | E63: Polad U-profil (şveller), U-profil 14П | F63: ton | G63: 0.3769 | H63: (Yalnız işçilik qiymətləndiriləcəkdir) | K63: 900 | L63: =(J63+K63)*G63 -> 339.21
B64: 1 | C64: 6 | D64: 2 | E64: Polad borular, Ø30 mm, divar qalınlığı 2 mm | F64: ton | G64: 0.0422 | H64: (Yalnız işçilik qiymətləndiriləcəkdir) | K64: 900 | L64: =(J64+K64)*G64 -> 37.98
B65: 1 | C65: 6 | D65: 3 | E65: Anker boltları M14, L = 250 mm | F65: ədəd | G65: 64 | H65: (Yalnız işçilik qiymətləndiriləcəkdir) | K65: 40 | L65: =(J65+K65)*G65 -> 2560
B66: 1 | C66: 6 | D66: 4 | E66: Polad lövhə t=10 mm | F66: ton | G66: 0.0926 | H66: (Yalnız işçilik qiymətləndiriləcəkdir) | K66: 900 | L66: =(J66+K66)*G66 -> 83.34
B67: 1 | C67: 6 | D67: 5 | E67: Polad lövhə t=4 mm | F67: ton | G67: 0.0472 | H67: (Yalnız işçilik qiymətləndiriləcəkdir) | K67: 900 | L67: =(J67+K67)*G67 -> 42.48

Sheet Offer_Auto
B2: ='0 - Summary'!A1 -> ŞIRKƏT ADI : "İNDUSTRİAL SERVİCES CONSTRUCTİON GROUP" MMC
J3: =J9='0 - Summary'!C14 -> #DIV/0!
B4: III HİSSƏ: ÖLÇÜLMÜŞ İŞLƏR / MEASURED WORKS
B5: Bənd | E5: Təsviri | F5: Vahid | G5: Miqdar | H5: Müqavilə məbləği | K5: Müqavilə məbləği
H6: Vahid material qiyməti | I6: Vahid işçilik qiyməti | J6: Cəmi məbləğ | K6: Ümumi material qiyməti | L6: Ümumi işçilik qiyməti | M6: Cəmi məbləğ
H7: AZN | K7: AZN
B8: 1 | E8: Bu bölmədə əsas işlərin material və işçilik xərcləri orta bazar qiymətləri əsasında, balanslaşdırılmış şəkildə dəyərləndirilməlidir. Qiymətləndirmə zamanı material itkisi, sərfiyyat normaları və əmsallar, işlə bağlı tələb olunan köməkçi materiallar, materialların daşınması eləcə də gömrükləmə xərcləri nəzərə alınmalıdır. Bu işlərə dair üstəlik və dolayı xərclər, şirkətin mənfəəti vahid qiymətlərə daxil edilməməlidir və qiymət cədvəlinin I ci və II hissələrində öz əksini tapmalıdır. Burada qeyd edilmiş miqdarlar indikativ xarakter daşıyır. Həcmlərin hesablanmasında Sifarişçi tərəfindən təqdim edilən İşlərin Təsvirinə və Texniki Sənədlərə istinad edilməli və aşağıdakılarla məhdudlaşmayaraq İşlərə aid bütün detallar nəzərə alınmalıdır.
E9: Bakı şəhəri, Abşeron rayonu, Bilgəh qəsəbəsi, Zəfəran savxozu ərazisində yerləşən Fərdi yaşayış evi Əsas Bina və İtlər evində Memari işlər | J9: =J10+J183 -> #DIV/0! | M9: =M10+M183 -> #DIV/0!
E10: Bakı şəhəri, Abşeron rayonu, Bilgəh qəsəbəsi, Zəfəran savxozu ərazisində yerləşən Fərdi yaşayış evi (Əsas Bina) Memarlıq və İnteryer işləri | J10: =J11+J67+J134+J169+J174 -> #DIV/0! | M10: =M11+M67+M134+M169+M174 -> #DIV/0!
B11: 1 | C11: 0 | D11: 0 | E11: Divar işləri | J11: =J12+J17+J21+J26+J31+J36+J41+J45+J50+J55+J60+J65 -> #DIV/0! | K11: =K12+K17+K21+K26+K31+K36+K41+K45+K50+K55+K60+K65 -> #DIV/0! | L11: =L12+L17+L21+L26+L31+L36+L41+L45+L50+L55+L60+L65 -> #REF! | M11: =M12+M17+M21+M26+M31+M36+M41+M45+M50+M55+M60+M65 -> #DIV/0!
B12: 1 | C12: 1 | D12: 0 | E12: WF-1 Divar tipi | J12: =SUM(J13:J16) -> #DIV/0! | K12: =SUM(K13:K16) -> #DIV/0! | L12: =SUM(L13:L16) -> #REF! | M12: =SUM(M13:M16) -> #DIV/0!
B13: 1 | C13: 1 | D13: 1 | E13: WF-1 Boya, Betek, Max RAL 9010 | F13: m2 | G13: 1298 | H13: ='1 - Direct_DK_BoQ'!J11*'0 - Summary'!$H$19 -> #DIV/0! | I13: ='1 - Direct_DK_BoQ'!K11*'0 - Summary'!$G$15 -> 28.644182 | J13: =(H13+I13)*G13 -> #DIV/0! | K13: =H13*G13 -> #DIV/0! | L13: =I13*G13 -> 37180.148 | M13: =SUM(K13:L13) -> #DIV/0!
B14: 1 | C14: 1 | D14: 2 | E14: Binder | F14: m2 | G14: 1298 | H14: ='1 - Direct_DK_BoQ'!#REF!*'0 - Summary'!$H$19 -> #REF! | I14: ='1 - Direct_DK_BoQ'!#REF!*'0 - Summary'!$G$15 -> #REF! | J14: =(H14+I14)*G14 -> #REF! | K14: =H14*G14 -> #REF! | L14: =I14*G14 -> #REF! | M14: =SUM(K14:L14) -> #REF!
B15: 1 | C15: 1 | D15: 3 | E15: Üzlük 3mm (Cilalanma daxildir) | F15: m2 | G15: 1298 | H15: ='1 - Direct_DK_BoQ'!#REF!*'0 - Summary'!$H$19 -> #REF! | I15: ='1 - Direct_DK_BoQ'!#REF!*'0 - Summary'!$G$15 -> #REF! | J15: =(H15+I15)*G15 -> #REF! | K15: =H15*G15 -> #REF! | L15: =I15*G15 -> #REF! | M15: =SUM(K15:L15) -> #REF!
B16: 1 | C16: 1 | D16: 4 | E16: Fuqa gips (Aralıq doldurma qarışığı), (Dərziband qiymətə daxildir) | F16: m2 | G16: 1298 | H16: ='1 - Direct_DK_BoQ'!#REF!*'0 - Summary'!$H$19 -> #REF! | I16: ='1 - Direct_DK_BoQ'!#REF!*'0 - Summary'!$G$15 -> #REF! | J16: =(H16+I16)*G16 -> #REF! | K16: =H16*G16 -> #REF! | L16: =I16*G16 -> #REF! | M16: =SUM(K16:L16) -> #REF!
B17: 1 | C17: 2 | D17: 0 | E17: WF-2 Divar tipi | J17: =SUM(J18:J20) -> #DIV/0! | K17: =SUM(K18:K20) -> #DIV/0! | L17: =SUM(L18:L20) -> #REF! | M17: =SUM(M18:M20) -> #DIV/0!
B18: 1 | C18: 2 | D18: 1 | E18: WF-2 Ceramogranit, Albatros 101601, Beton texture, 60x120cm (Sadəcə işçilik üçün qiymət veiləcəkdir) | F18: m2 | G18: 49 | H18: ='1 - Direct_DK_BoQ'!J14*'0 - Summary'!$H$19 -> #DIV/0! | I18: ='1 - Direct_DK_BoQ'!K14*'0 - Summary'!$G$15 -> 12.53183 | J18: =(H18+I18)*G18 -> #DIV/0! | K18: =H18*G18 -> #DIV/0! | L18: =I18*G18 -> 614.05965 | M18: =SUM(K18:L18) -> #DIV/0!
B19: 1 | C19: 2 | D19: 2 | E19: Yapışdırıcı material 8m | F19: m2 | G19: 49 | H19: ='1 - Direct_DK_BoQ'!#REF!*'0 - Summary'!$H$19 -> #REF! | I19: ='1 - Direct_DK_BoQ'!#REF!*'0 - Summary'!$G$15 -> #REF! | J19: =(H19+I19)*G19 -> #REF! | K19: =H19*G19 -> #REF! | L19: =I19*G19 -> #REF! | M19: =SUM(K19:L19) -> #REF!
B20: 1 | C20: 2 | D20: 3 | E20: Sürmə Hidroizolyasiya qatı | F20: m2 | G20: 49 | H20: ='1 - Direct_DK_BoQ'!#REF!*'0 - Summary'!$H$19 -> #REF! | I20: ='1 - Direct_DK_BoQ'!#REF!*'0 - Summary'!$G$15 -> #REF! | J20: =(H20+I20)*G20 -> #REF! | K20: =H20*G20 -> #REF! | L20: =I20*G20 -> #REF! | M20: =SUM(K20:L20) -> #REF!
B21: 1 | C21: 3 | D21: 0 | E21: WF-3 Divar tipi | J21: =SUM(J22:J24) -> #DIV/0! | K21: =SUM(K22:K24) -> #DIV/0! | L21: =SUM(L22:L24) -> #REF! | M21: =SUM(M22:M24) -> #DIV/0!
B22: 1 | C22: 3 | D22: 1 | E22: WF-3 Plaster, Pitted PT L0006, Armourcoat | F22: m2 | G22: 1096 | H22: ='1 - Direct_DK_BoQ'!J17*'0 - Summary'!$H$19 -> #DIV/0! | I22: ='1 - Direct_DK_BoQ'!K17*'0 - Summary'!$G$15 -> 7.1610455 | J22: =(H22+I22)*G22 -> #DIV/0! | K22: =H22*G22 -> #DIV/0! | L22: =I22*G22 -> 7848.5059 | M22: =SUM(K22:L22) -> #DIV/0!
B23: 1 | C23: 3 | D23: 2 | E23: Binder | F23: m2 | G23: 1096 | H23: ='1 - Direct_DK_BoQ'!J18*'0 - Summary'!$H$19 -> #DIV/0! | I23: ='1 - Direct_DK_BoQ'!K18*'0 - Summary'!$G$15 -> 17.902614 | J23: =(H23+I23)*G23 -> #DIV/0! | K23: =H23*G23 -> #DIV/0! | L23: =I23*G23 -> 19621.265 | M23: =SUM(K23:L23) -> #DIV/0!
B24: 1 | C24: 3 | D24: 3 | E24: Üzlük 3mm (Cilalanma daxildir) | F24: m2 | G24: 1096 | H24: ='1 - Direct_DK_BoQ'!#REF!*'0 - Summary'!$H$19 -> #REF! | I24: ='1 - Direct_DK_BoQ'!#REF!*'0 - Summary'!$G$15 -> #REF! | J24: =(H24+I24)*G24 -> #REF! | K24: =H24*G24 -> #REF! | L24: =I24*G24 -> #REF! | M24: =SUM(K24:L24) -> #REF!
B25: 1 | C25: 3 | D25: 4 | E25: Fuqa gips (Aralıq doldurma qarışığı), (Dərziband qiymətə daxildir) | F25: m2 | G25: 1096 | H25: ='1 - Direct_DK_BoQ'!#REF!*'0 - Summary'!$H$19 -> #REF! | I25: ='1 - Direct_DK_BoQ'!#REF!*'0 - Summary'!$G$15 -> #REF! | J25: =(H25+I25)*G25 -> #REF! | K25: =H25*G25 -> #REF! | L25: =I25*G25 -> #REF! | M25: =SUM(K25:L25) -> #REF!
B26: 1 | C26: 4 | D26: 0 | E26: WF-4 Divar tipi | J26: =SUM(J27:J29) -> #DIV/0! | K26: =SUM(K27:K29) -> #DIV/0! | L26: =SUM(L27:L29) -> #REF! | M26: =SUM(M27:M29) -> #DIV/0!
B27: 1 | C27: 4 | D27: 1 | E27: WF-4 Boya, TIKV Tikkurila, WhiteTikkurila | F27: m2 | G27: 892 | H27: ='1 - Direct_DK_BoQ'!J20*'0 - Summary'!$H$19 -> #DIV/0! | I27: ='1 - Direct_DK_BoQ'!K20*'0 - Summary'!$G$15 -> 32.224705 | J27: =(H27+I27)*G27 -> #DIV/0! | K27: =H27*G27 -> #DIV/0! | L27: =I27*G27 -> 28744.437 | M27: =SUM(K27:L27) -> #DIV/0!
B28: 1 | C28: 4 | D28: 2 | E28: Binder | F28: m2 | G28: 892 | H28: ='1 - Direct_DK_BoQ'!J21*'0 - Summary'!$H$19 -> #DIV/0! | I28: ='1 - Direct_DK_BoQ'!K21*'0 - Summary'!$G$15 -> 25.063659 | J28: =(H28+I28)*G28 -> #DIV/0! | K28: =H28*G28 -> #DIV/0! | L28: =I28*G28 -> 22356.784 | M28: =SUM(K28:L28) -> #DIV/0!
B29: 1 | C29: 4 | D29: 3 | E29: Üzlük 3mm (Cilalanma daxildir) | F29: m2 | G29: 892 | H29: ='1 - Direct_DK_BoQ'!#REF!*'0 - Summary'!$H$19 -> #REF! | I29: ='1 - Direct_DK_BoQ'!#REF!*'0 - Summary'!$G$15 -> #REF! | J29: =(H29+I29)*G29 -> #REF! | K29: =H29*G29 -> #REF! | L29: =I29*G29 -> #REF! | M29: =SUM(K29:L29) -> #REF!
B30: 1 | C30: 4 | D30: 4 | E30: Fuqa gips (Aralıq doldurma qarışığı), (Dərziband qiymətə daxildir) | F30: m2 | G30: 892 | H30: ='1 - Direct_DK_BoQ'!#REF!*'0 - Summary'!$H$19 -> #REF! | I30: ='1 - Direct_DK_BoQ'!#REF!*'0 - Summary'!$G$15 -> #REF! | J30: =(H30+I30)*G30 -> #REF! | K30: =H30*G30 -> #REF! | L30: =I30*G30 -> #REF! | M30: =SUM(K30:L30) -> #REF!
B31: 1 | C31: 5 | D31: 0 | E31: WF-5 Divar tipi | J31: =SUM(J32:J34) -> #DIV/0! | K31: =SUM(K32:K34) -> #DIV/0! | L31: =SUM(L32:L34) -> #REF! | M31: =SUM(M32:M34) -> #DIV/0!
B32: 1 | C32: 5 | D32: 1 | E32: WF-5 Panel, , BespokeWood Wall Panel (Panelin quraşdırılması üçün alt materiallar qiymətə daxildir), (Sadəcə işçilik üçün qiymət veiləcəkdir) | F32: m2 | G32: 83 | H32: ='1 - Direct_DK_BoQ'!J26*'0 - Summary'!$H$19 -> #DIV/0! | I32: ='1 - Direct_DK_BoQ'!K26*'0 - Summary'!$G$15 -> 0 | J32: =(H32+I32)*G32 -> #DIV/0! | K32: =H32*G32 -> #DIV/0! | L32: =I32*G32 -> 0 | M32: =SUM(K32:L32) -> #DIV/0!
B33: 1 | C33: 5 | D33: 2 | E33: Binder | F33: m2 | G33: 83 | H33: ='1 - Direct_DK_BoQ'!#REF!*'0 - Summary'!$H$19 -> #REF! | I33: ='1 - Direct_DK_BoQ'!#REF!*'0 - Summary'!$G$15 -> #REF! | J33: =(H33+I33)*G33 -> #REF! | K33: =H33*G33 -> #REF! | L33: =I33*G33 -> #REF! | M33: =SUM(K33:L33) -> #REF!
B34: 1 | C34: 5 | D34: 3 | E34: Üzlük 3mm (Cilalanma daxildir) | F34: m2 | G34: 83 | H34: ='1 - Direct_DK_BoQ'!#REF!*'0 - Summary'!$H$19 -> #REF! | I34: ='1 - Direct_DK_BoQ'!#REF!*'0 - Summary'!$G$15 -> #REF! | J34: =(H34+I34)*G34 -> #REF! | K34: =H34*G34 -> #REF! | L34: =I34*G34 -> #REF! | M34: =SUM(K34:L34) -> #REF!
B35: 1 | C35: 5 | D35: 4 | E35: Fuqa gips (Aralıq doldurma qarışığı), (Dərziband qiymətə daxildir) | F35: m2 | G35: 83 | H35: ='1 - Direct_DK_BoQ'!#REF!*'0 - Summary'!$H$19 -> #REF! | I35: ='1 - Direct_DK_BoQ'!#REF!*'0 - Summary'!$G$15 -> #REF! | J35: =(H35+I35)*G35 -> #REF! | K35: =H35*G35 -> #REF! | L35: =I35*G35 -> #REF! | M35: =SUM(K35:L35) -> #REF!
B36: 1 | C36: 6 | D36: 0 | E36: WF-6 Divar tipi | J36: =SUM(J37:J39) -> #DIV/0! | K36: =SUM(K37:K39) -> #DIV/0! | L36: =SUM(L37:L39) -> #REF! | M36: =SUM(M37:M39) -> #DIV/0!
B37: 1 | C37: 6 | D37: 1 | E37: WF-6 Panel, Bespoke, Wood Wall Panel (Panelin quraşdırılması üçün alt materiallar qiymətə daxildir) (Sadəcə işçilik üçün qiymət veiləcəkdir) | F37: m2 | G37: 43 | H37: ='1 - Direct_DK_BoQ'!J63*'0 - Summary'!$H$19 -> #DIV/0! | I37: ='1 - Direct_DK_BoQ'!K63*'0 - Summary'!$G$15 -> 3222.4705 | J37: =(H37+I37)*G37 -> #DIV/0! | K37: =H37*G37 -> #DIV/0! | L37: =I37*G37 -> 138566.23 | M37: =SUM(K37:L37) -> #DIV/0!
B38: 1 | C38: 6 | D38: 2 | E38: Binder | F38: m2 | G38: 43 | H38: ='1 - Direct_DK_BoQ'!J64*'0 - Summary'!$H$19 -> #DIV/0! | I38: ='1 - Direct_DK_BoQ'!K64*'0 - Summary'!$G$15 -> 3222.4705 | J38: =(H38+I38)*G38 -> #DIV/0! | K38: =H38*G38 -> #DIV/0! | L38: =I38*G38 -> 138566.23 | M38: =SUM(K38:L38) -> #DIV/0!
B39: 1 | C39: 6 | D39: 3 | E39: Üzlük 3mm (Cilalanma daxildir) | F39: m2 | G39: 43 | H39: ='1 - Direct_DK_BoQ'!#REF!*'0 - Summary'!$H$19 -> #REF! | I39: ='1 - Direct_DK_BoQ'!#REF!*'0 - Summary'!$G$15 -> #REF! | J39: =(H39+I39)*G39 -> #REF! | K39: =H39*G39 -> #REF! | L39: =I39*G39 -> #REF! | M39: =SUM(K39:L39) -> #REF!
B40: 1 | C40: 6 | D40: 4 | E40: Fuqa gips (Aralıq doldurma qarışığı), (Dərziband qiymətə daxildir) | F40: m2 | G40: 43 | H40: ='1 - Direct_DK_BoQ'!#REF!*'0 - Summary'!$H$19 -> #REF! | I40: ='1 - Direct_DK_BoQ'!#REF!*'0 - Summary'!$G$15 -> #REF! | J40: =(H40+I40)*G40 -> #REF! | K40: =H40*G40 -> #REF! | L40: =I40*G40 -> #REF! | M40: =SUM(K40:L40) -> #REF!
B41: 1 | C41: 7 | D41: 0 | E41: WF-19 Divar tipi | J41: =SUM(J42:J44) -> #REF! | K41: =SUM(K42:K44) -> #REF! | L41: =SUM(L42:L44) -> #REF! | M41: =SUM(M42:M44) -> #REF!
B42: 1 | C42: 7 | D42: 1 | E42: WF-19 Natural Stone, Travertino Décor | F42: m2 | G42: 9 | H42: ='1 - Direct_DK_BoQ'!#REF!*'0 - Summary'!$H$19 -> #REF! | I42: ='1 - Direct_DK_BoQ'!#REF!*'0 - Summary'!$G$15 -> #REF! | J42: =(H42+I42)*G42 -> #REF! | K42: =H42*G42 -> #REF! | L42: =I42*G42 -> #REF! | M42: =SUM(K42:L42) -> #REF!
B43: 1 | C43: 7 | D43: 2 | E43: Yapışdırıcı material 8m | F43: m2 | G43: 9 | H43: ='1 - Direct_DK_BoQ'!#REF!*'0 - Summary'!$H$19 -> #REF! | I43: ='1 - Direct_DK_BoQ'!#REF!*'0 - Summary'!$G$15 -> #REF! | J43: =(H43+I43)*G43 -> #REF! | K43: =H43*G43 -> #REF! | L43: =I43*G43 -> #REF! | M43: =SUM(K43:L43) -> #REF!
B44: 1 | C44: 7 | D44: 3 | E44: Sürmə Hidroizolyasiya qatı | F44: m2 | G44: 9 | H44: ='1 - Direct_DK_BoQ'!#REF!*'0 - Summary'!$H$19 -> #REF! | I44: ='1 - Direct_DK_BoQ'!#REF!*'0 - Summary'!$G$15 -> #REF! | J44: =(H44+I44)*G44 -> #REF! | K44: =H44*G44 -> #REF! | L44: =I44*G44 -> #REF! | M44: =SUM(K44:L44) -> #REF!
B45: 1 | C45: 8 | D45: 0 | E45: WF-20 Divar tipi | J45: =SUM(J46:J48) -> #REF! | K45: =SUM(K46:K48) -> #REF! | L45: =SUM(L46:L48) -> #REF! | M45: =SUM(M46:M48) -> #REF!
B46: 1 | C46: 8 | D46: 1 | E46: WF-20 Divar kağızı, Sanderson, CANTALOUPE ENGLISH GREY 216761 (Sadəcə işçilik üçün qiymət veiləcəkdir) | F46: m2 | G46: 8 | H46: ='1 - Direct_DK_BoQ'!#REF!*'0 - Summary'!$H$19 -> #REF! | I46: ='1 - Direct_DK_BoQ'!#REF!*'0 - Summary'!$G$15 -> #REF! | J46: =(H46+I46)*G46 -> #REF! | K46: =H46*G46 -> #REF! | L46: =I46*G46 -> #REF! | M46: =SUM(K46:L46) -> #REF!
B47: 1 | C47: 8 | D47: 2 | E47: Binder | F47: m2 | G47: 8 | H47: ='1 - Direct_DK_BoQ'!#REF!*'0 - Summary'!$H$19 -> #REF! | I47: ='1 - Direct_DK_BoQ'!#REF!*'0 - Summary'!$G$15 -> #REF! | J47: =(H47+I47)*G47 -> #REF! | K47: =H47*G47 -> #REF! | L47: =I47*G47 -> #REF! | M47: =SUM(K47:L47) -> #REF!
B48: 1 | C48: 8 | D48: 3 | E48: Üzlük 3mm (Cilalanma daxildir) | F48: m2 | G48: 8 | H48: ='1 - Direct_DK_BoQ'!#REF!*'0 - Summary'!$H$19 -> #REF! | I48: ='1 - Direct_DK_BoQ'!#REF!*'0 - Summary'!$G$15 -> #REF! | J48: =(H48+I48)*G48 -> #REF! | K48: =H48*G48 -> #REF! | L48: =I48*G48 -> #REF! | M48: =SUM(K48:L48) -> #REF!
B49: 1 | C49: 8 | D49: 4 | E49: Fuqa gips (Aralıq doldurma qarışığı), (Dərziband qiymətə daxildir) | F49: m2 | G49: 8 | H49: ='1 - Direct_DK_BoQ'!#REF!*'0 - Summary'!$H$19 -> #REF! | I49: ='1 - Direct_DK_BoQ'!#REF!*'0 - Summary'!$G$15 -> #REF! | J49: =(H49+I49)*G49 -> #REF! | K49: =H49*G49 -> #REF! | L49: =I49*G49 -> #REF! | M49: =SUM(K49:L49) -> #REF!
B50: 1 | C50: 9 | D50: 0 | E50: WF-25 Divar tipi | J50: =SUM(J51:J53) -> #REF! | K50: =SUM(K51:K53) -> #REF! | L50: =SUM(L51:L53) -> #REF! | M50: =SUM(M51:M53) -> #REF!
B51: 1 | C51: 9 | D51: 1 | E51: WF-25 Acoustic Plaster, AAC 10179, Armourcoat | F51: m2 | G51: 55 | H51: ='1 - Direct_DK_BoQ'!#REF!*'0 - Summary'!$H$19 -> #REF! | I51: ='1 - Direct_DK_BoQ'!#REF!*'0 - Summary'!$G$15 -> #REF! | J51: =(H51+I51)*G51 -> #REF! | K51: =H51*G51 -> #REF! | L51: =I51*G51 -> #REF! | M51: =SUM(K51:L51) -> #REF!
B52: 1 | C52: 9 | D52: 2 | E52: Binder | F52: m2 | G52: 55 | H52: ='1 - Direct_DK_BoQ'!#REF!*'0 - Summary'!$H$19 -> #REF! | I52: ='1 - Direct_DK_BoQ'!#REF!*'0 - Summary'!$G$15 -> #REF! | J52: =(H52+I52)*G52 -> #REF! | K52: =H52*G52 -> #REF! | L52: =I52*G52 -> #REF! | M52: =SUM(K52:L52) -> #REF!
B53: 1 | C53: 9 | D53: 3 | E53: Üzlük 3mm (Cilalanma daxildir) | F53: m2 | G53: 55 | H53: ='1 - Direct_DK_BoQ'!#REF!*'0 - Summary'!$H$19 -> #REF! | I53: ='1 - Direct_DK_BoQ'!#REF!*'0 - Summary'!$G$15 -> #REF! | J53: =(H53+I53)*G53 -> #REF! | K53: =H53*G53 -> #REF! | L53: =I53*G53 -> #REF! | M53: =SUM(K53:L53) -> #REF!
B54: 1 | C54: 9 | D54: 4 | E54: Fuqa gips (Aralıq doldurma qarışığı), (Dərziband qiymətə daxildir) | F54: m2 | G54: 55 | H54: ='1 - Direct_DK_BoQ'!#REF!*'0 - Summary'!$H$19 -> #REF! | I54: ='1 - Direct_DK_BoQ'!#REF!*'0 - Summary'!$G$15 -> #REF! | J54: =(H54+I54)*G54 -> #REF! | K54: =H54*G54 -> #REF! | L54: =I54*G54 -> #REF! | M54: =SUM(K54:L54) -> #REF!
B55: 1 | C55: 10 | D55: 0 | E55: WF-27 Divar tipi | J55: =SUM(J56:J58) -> #REF! | K55: =SUM(K56:K58) -> #REF! | L55: =SUM(L56:L58) -> #REF! | M55: =SUM(M56:M58) -> #REF!
B56: 1 | C56: 10 | D56: 1 | E56: WF-27 Paint Luja 7 SKU 699 White (Waterproof), Tikkurila | F56: m2 | G56: 160 | H56: ='1 - Direct_DK_BoQ'!#REF!*'0 - Summary'!$H$19 -> #REF! | I56: ='1 - Direct_DK_BoQ'!#REF!*'0 - Summary'!$G$15 -> #REF! | J56: =(H56+I56)*G56 -> #REF! | K56: =H56*G56 -> #REF! | L56: =I56*G56 -> #REF! | M56: =SUM(K56:L56) -> #REF!
B57: 1 | C57: 10 | D57: 2 | E57: Binder | F57: m2 | G57: 160 | H57: ='1 - Direct_DK_BoQ'!#REF!*'0 - Summary'!$H$19 -> #REF! | I57: ='1 - Direct_DK_BoQ'!#REF!*'0 - Summary'!$G$15 -> #REF! | J57: =(H57+I57)*G57 -> #REF! | K57: =H57*G57 -> #REF! | L57: =I57*G57 -> #REF! | M57: =SUM(K57:L57) -> #REF!
B58: 1 | C58: 10 | D58: 3 | E58: Üzlük 3mm (Cilalanma daxildir) | F58: m2 | G58: 160 | H58: ='1 - Direct_DK_BoQ'!#REF!*'0 - Summary'!$H$19 -> #REF! | I58: ='1 - Direct_DK_BoQ'!#REF!*'0 - Summary'!$G$15 -> #REF! | J58: =(H58+I58)*G58 -> #REF! | K58: =H58*G58 -> #REF! | L58: =I58*G58 -> #REF! | M58: =SUM(K58:L58) -> #REF!
B59: 1 | C59: 10 | D59: 4 | E59: Fuqa gips (Aralıq doldurma qarışığı), (Dərziband qiymətə daxildir) | F59: m2 | G59: 160 | H59: ='1 - Direct_DK_BoQ'!#REF!*'0 - Summary'!$H$19 -> #REF! | I59: ='1 - Direct_DK_BoQ'!#REF!*'0 - Summary'!$G$15 -> #REF! | J59: =(H59+I59)*G59 -> #REF! | K59: =H59*G59 -> #REF! | L59: =I59*G59 -> #REF! | M59: =SUM(K59:L59) -> #REF!
B60: 1 | C60: 11 | D60: 0 | E60: WF-27.3 Divar tipi | J60: =SUM(J61:J63) -> #REF! | K60: =SUM(K61:K63) -> #REF! | L60: =SUM(L61:L63) -> #REF! | M60: =SUM(M61:M63) -> #REF!
B61: 1 | C61: 11 | D61: 1 | E61: WF-27.3 Paint, F503 Waterproof, TikTikkurila Waterproofkurila | F61: m2 | G61: 27 | H61: ='1 - Direct_DK_BoQ'!#REF!*'0 - Summary'!$H$19 -> #REF! | I61: ='1 - Direct_DK_BoQ'!#REF!*'0 - Summary'!$G$15 -> #REF! | J61: =(H61+I61)*G61 -> #REF! | K61: =H61*G61 -> #REF! | L61: =I61*G61 -> #REF! | M61: =SUM(K61:L61) -> #REF!
B62: 1 | C62: 11 | D62: 2 | E62: Binder | F62: m2 | G62: 27 | H62: ='1 - Direct_DK_BoQ'!#REF!*'0 - Summary'!$H$19 -> #REF! | I62: ='1 - Direct_DK_BoQ'!#REF!*'0 - Summary'!$G$15 -> #REF! | J62: =(H62+I62)*G62 -> #REF! | K62: =H62*G62 -> #REF! | L62: =I62*G62 -> #REF! | M62: =SUM(K62:L62) -> #REF!
B63: 1 | C63: 11 | D63: 3 | E63: Üzlük 3mm (Cilalanma daxildir) | F63: m2 | G63: 27 | H63: ='1 - Direct_DK_BoQ'!#REF!*'0 - Summary'!$H$19 -> #REF! | I63: ='1 - Direct_DK_BoQ'!#REF!*'0 - Summary'!$G$15 -> #REF! | J63: =(H63+I63)*G63 -> #REF! | K63: =H63*G63 -> #REF! | L63: =I63*G63 -> #REF! | M63: =SUM(K63:L63) -> #REF!
B64: 1 | C64: 11 | D64: 4 | E64: Fuqa gips (Aralıq doldurma qarışığı), (Dərziband qiymətə daxildir) | F64: m2 | G64: 27 | H64: ='1 - Direct_DK_BoQ'!#REF!*'0 - Summary'!$H$19 -> #REF! | I64: ='1 - Direct_DK_BoQ'!#REF!*'0 - Summary'!$G$15 -> #REF! | J64: =(H64+I64)*G64 -> #REF! | K64: =H64*G64 -> #REF! | L64: =I64*G64 -> #REF! | M64: =SUM(K64:L64) -> #REF!
B65: 1 | C65: 12 | D65: 0 | E65: WF-8 Divar tipi | J65: =SUM(J66:J68) -> #REF! | K65: =SUM(K66:K68) -> #REF! | L65: =SUM(L66:L68) -> #REF! | M65: =SUM(M66:M68) -> #REF!
B66: 1 | C66: 12 | D66: 1 | E66: Mirror, Custom Made (Bütün alt materialları qiymətə daxildir) | F66: m2 | G66: 55 | H66: ='1 - Direct_DK_BoQ'!#REF!*'0 - Summary'!$H$19 -> #REF! | I66: ='1 - Direct_DK_BoQ'!#REF!*'0 - Summary'!$G$15 -> #REF! | J66: =(H66+I66)*G66 -> #REF! | K66: =H66*G66 -> #REF! | L66: =I66*G66 -> #REF! | M66: =SUM(K66:L66) -> #REF!
B67: 2 | C67: 0 | D67: 0 | E67: Döşəmə işləri | J67: =J68+J74+J81+J86+J91+J97+J104+J111+J117+J122+J128 -> #REF! | K67: =K68+K74+K81+K86+K91+K97+K104+K111+K117+K122+K128 -> #REF! | L67: =L68+L74+L81+L86+L91+L97+L104+L111+L117+L122+L128 -> #REF! | M67: =M68+M74+M81+M86+M91+M97+M104+M111+M117+M122+M128 -> #REF!
B68: 2 | C68: 1 | D68: 0 | E68: F-1 Laminat tipi | J68: =SUM(J69:J71) -> #REF! | K68: =SUM(K69:K71) -> #REF! | L68: =SUM(L69:L71) -> #REF! | M68: =SUM(M69:M71) -> #REF!
B69: 2 | C69: 1 | D69: 1 | E69: Laminat (Sadəcə işçilik üçün qiymət veiləcəkdir) | F69: m2 | G69: 116 | H69: ='1 - Direct_DK_BoQ'!#REF!*'0 - Summary'!$H$19 -> #REF! | I69: ='1 - Direct_DK_BoQ'!#REF!*'0 - Summary'!$G$15 -> #REF! | J69: =(H69+I69)*G69 -> #REF! | K69: =H69*G69 -> #REF! | L69: =I69*G69 -> #REF! | M69: =SUM(K69:L69) -> #REF!
B70: 2 | C70: 1 | D70: 2 | E70: Probka qatı - 2 mm | F70: m2 | G70: 116 | H70: ='1 - Direct_DK_BoQ'!#REF!*'0 - Summary'!$H$19 -> #REF! | I70: ='1 - Direct_DK_BoQ'!#REF!*'0 - Summary'!$G$15 -> #REF! | J70: =(H70+I70)*G70 -> #REF! | K70: =H70*G70 -> #REF! | L70: =I70*G70 -> #REF! | M70: =SUM(K70:L70) -> #REF!
B71: 2 | C71: 1 | D71: 3 | E71: Metal torla gücləndirilmiş sement-qum məhlulundan hamarlayıcı qat - 86mm | F71: m2 | G71: 116 | H71: ='1 - Direct_DK_BoQ'!#REF!*'0 - Summary'!$H$19 -> #REF! | I71: ='1 - Direct_DK_BoQ'!#REF!*'0 - Summary'!$G$15 -> #REF! | J71: =(H71+I71)*G71 -> #REF! | K71: =H71*G71 -> #REF! | L71: =I71*G71 -> #REF! | M71: =SUM(K71:L71) -> #REF!
B72: 2 | C72: 1 | D72: 4 | E72: XPS paneli - 50mm | F72: m2 | G72: 116 | H72: ='1 - Direct_DK_BoQ'!#REF!*'0 - Summary'!$H$19 -> #REF! | I72: ='1 - Direct_DK_BoQ'!#REF!*'0 - Summary'!$G$15 -> #REF! | J72: =(H72+I72)*G72 -> #REF! | K72: =H72*G72 -> #REF! | L72: =I72*G72 -> #REF! | M72: =SUM(K72:L72) -> #REF!
B73: 2 | C73: 1 | D73: 5 | E73: Hidroizolyasiya qatı | F73: m2 | G73: 116 | H73: ='1 - Direct_DK_BoQ'!#REF!*'0 - Summary'!$H$19 -> #REF! | I73: ='1 - Direct_DK_BoQ'!#REF!*'0 - Summary'!$G$15 -> #REF! | J73: =(H73+I73)*G73 -> #REF! | K73: =H73*G73 -> #REF! | L73: =I73*G73 -> #REF! | M73: =SUM(K73:L73) -> #REF!
B74: 2 | C74: 2 | D74: 0 | E74: F-2 Keromaqranit | J74: =SUM(J75:J77) -> #REF! | K74: =SUM(K75:K77) -> #REF! | L74: =SUM(L75:L77) -> #REF! | M74: =SUM(M75:M77) -> #REF!
B75: 2 | C75: 2 | D75: 1 | E75: Ceramogranit, 600 x 1200 mm x10 mm (Sadəcə işçilik üçün qiymət veiləcəkdir) | F75: m2 | G75: 16 | H75: ='1 - Direct_DK_BoQ'!#REF!*'0 - Summary'!$H$19 -> #REF! | I75: ='1 - Direct_DK_BoQ'!#REF!*'0 - Summary'!$G$15 -> #REF! | J75: =(H75+I75)*G75 -> #REF! | K75: =H75*G75 -> #REF! | L75: =I75*G75 -> #REF! | M75: =SUM(K75:L75) -> #REF!
B76: 2 | C76: 2 | D76: 2 | E76: Yapışdırıcı qat -5mm | F76: m2 | G76: 16 | H76: ='1 - Direct_DK_BoQ'!#REF!*'0 - Summary'!$H$19 -> #REF! | I76: ='1 - Direct_DK_BoQ'!#REF!*'0 - Summary'!$G$15 -> #REF! | J76: =(H76+I76)*G76 -> #REF! | K76: =H76*G76 -> #REF! | L76: =I76*G76 -> #REF! | M76: =SUM(K76:L76) -> #REF!
B77: 2 | C77: 2 | D77: 3 | E77: Suqoruyucu qat - İzolateks | F77: m2 | G77: 16 | H77: ='1 - Direct_DK_BoQ'!#REF!*'0 - Summary'!$H$19 -> #REF! | I77: ='1 - Direct_DK_BoQ'!#REF!*'0 - Summary'!$G$15 -> #REF! | J77: =(H77+I77)*G77 -> #REF! | K77: =H77*G77 -> #REF! | L77: =I77*G77 -> #REF! | M77: =SUM(K77:L77) -> #REF!
B78: 2 | C78: 2 | D78: 4 | E78: Metal torla güclındirilmiş hamarlayıcı qat (qızdırıcı elementlərlə) - 115mm | F78: m2 | G78: 16 | H78: ='1 - Direct_DK_BoQ'!#REF!*'0 - Summary'!$H$19 -> #REF! | I78: ='1 - Direct_DK_BoQ'!#REF!*'0 - Summary'!$G$15 -> #REF! | J78: =(H78+I78)*G78 -> #REF! | K78: =H78*G78 -> #REF! | L78: =I78*G78 -> #REF! | M78: =SUM(K78:L78) -> #REF!
B79: 2 | C79: 2 | D79: 5 | E79: XPS panelləri - 20mm | F79: m2 | G79: 16 | H79: ='1 - Direct_DK_BoQ'!#REF!*'0 - Summary'!$H$19 -> #REF! | I79: ='1 - Direct_DK_BoQ'!#REF!*'0 - Summary'!$G$15 -> #REF! | J79: =(H79+I79)*G79 -> #REF! | K79: =H79*G79 -> #REF! | L79: =I79*G79 -> #REF! | M79: =SUM(K79:L79) -> #REF!
B80: 2 | C80: 2 | D80: 6 | E80: Hidroizolyasiya qatı | F80: m2 | G80: 16 | H80: ='1 - Direct_DK_BoQ'!#REF!*'0 - Summary'!$H$19 -> #REF! | I80: ='1 - Direct_DK_BoQ'!#REF!*'0 - Summary'!$G$15 -> #REF! | J80: =(H80+I80)*G80 -> #REF! | K80: =H80*G80 -> #REF! | L80: =I80*G80 -> #REF! | M80: =SUM(K80:L80) -> #REF!
B81: 2 | C81: 3 | D81: 0 | E81: F-3 Epoksid döşəmə (Koridor) | J81: =SUM(J82:J84) -> #REF! | K81: =SUM(K82:K84) -> #REF! | L81: =SUM(L82:L84) -> #REF! | M81: =SUM(M82:M84) -> #REF!
B82: 2 | C82: 3 | D82: 1 | E82: Epoksi döşəmə (imitating concrete) | F82: m2 | G82: 163.4 | H82: ='1 - Direct_DK_BoQ'!#REF!*'0 - Summary'!$H$19 -> #REF! | I82: ='1 - Direct_DK_BoQ'!#REF!*'0 - Summary'!$G$15 -> #REF! | J82: =(H82+I82)*G82 -> #REF! | K82: =H82*G82 -> #REF! | L82: =I82*G82 -> #REF! | M82: =SUM(K82:L82) -> #REF!
B83: 2 | C83: 3 | D83: 2 | E83: Sement-qum məhlulundan hamarlayıcıı qat - 97 mm | F83: m2 | G83: 163.4 | H83: ='1 - Direct_DK_BoQ'!#REF!*'0 - Summary'!$H$19 -> #REF! | I83: ='1 - Direct_DK_BoQ'!#REF!*'0 - Summary'!$G$15 -> #REF! | J83: =(H83+I83)*G83 -> #REF! | K83: =H83*G83 -> #REF! | L83: =I83*G83 -> #REF! | M83: =SUM(K83:L83) -> #REF!
B84: 2 | C84: 3 | D84: 3 | E84: XPS panelləri - 50 mm | F84: m2 | G84: 163.4 | H84: ='1 - Direct_DK_BoQ'!#REF!*'0 - Summary'!$H$19 -> #REF! | I84: ='1 - Direct_DK_BoQ'!#REF!*'0 - Summary'!$G$15 -> #REF! | J84: =(H84+I84)*G84 -> #REF! | K84: =H84*G84 -> #REF! | L84: =I84*G84 -> #REF! | M84: =SUM(K84:L84) -> #REF!
B85: 2 | C85: 3 | D85: 4 | E85: Hidroizolyasiya qatı | F85: m2 | G85: 163.4 | H85: ='1 - Direct_DK_BoQ'!#REF!*'0 - Summary'!$H$19 -> #REF! | I85: ='1 - Direct_DK_BoQ'!#REF!*'0 - Summary'!$G$15 -> #REF! | J85: =(H85+I85)*G85 -> #REF! | K85: =H85*G85 -> #REF! | L85: =I85*G85 -> #REF! | M85: =SUM(K85:L85) -> #REF!
B86: 2 | C86: 4 | D86: 0 | E86: F-3 Epoksid döşəmə | J86: =SUM(J87:J89) -> #REF! | K86: =SUM(K87:K89) -> #REF! | L86: =SUM(L87:L89) -> #REF! | M86: =SUM(M87:M89) -> #REF!
B87: 2 | C87: 4 | D87: 1 | E87: Epoksi döşəmə (imitating concrete) | F87: m2 | G87: 28.6 | H87: ='1 - Direct_DK_BoQ'!#REF!*'0 - Summary'!$H$19 -> #REF! | I87: ='1 - Direct_DK_BoQ'!#REF!*'0 - Summary'!$G$15 -> #REF! | J87: =(H87+I87)*G87 -> #REF! | K87: =H87*G87 -> #REF! | L87: =I87*G87 -> #REF! | M87: =SUM(K87:L87) -> #REF!
B88: 2 | C88: 4 | D88: 2 | E88: Sement-qum məhlulundan hamarlayıcıı qat - 97 mm | F88: m2 | G88: 28.6 | H88: ='1 - Direct_DK_BoQ'!#REF!*'0 - Summary'!$H$19 -> #REF! | I88: ='1 - Direct_DK_BoQ'!#REF!*'0 - Summary'!$G$15 -> #REF! | J88: =(H88+I88)*G88 -> #REF! | K88: =H88*G88 -> #REF! | L88: =I88*G88 -> #REF! | M88: =SUM(K88:L88) -> #REF!
B89: 2 | C89: 4 | D89: 3 | E89: XPS panelləri - 50 mm | F89: m2 | G89: 28.6 | H89: ='1 - Direct_DK_BoQ'!#REF!*'0 - Summary'!$H$19 -> #REF! | I89: ='1 - Direct_DK_BoQ'!#REF!*'0 - Summary'!$G$15 -> #REF! | J89: =(H89+I89)*G89 -> #REF! | K89: =H89*G89 -> #REF! | L89: =I89*G89 -> #REF! | M89: =SUM(K89:L89) -> #REF!
B90: 2 | C90: 4 | D90: 4 | E90: Hidroizolyasiya qatı | F90: m2 | G90: 28.6 | H90: ='1 - Direct_DK_BoQ'!#REF!*'0 - Summary'!$H$19 -> #REF! | I90: ='1 - Direct_DK_BoQ'!#REF!*'0 - Summary'!$G$15 -> #REF! | J90: =(H90+I90)*G90 -> #REF! | K90: =H90*G90 -> #REF! | L90: =I90*G90 -> #REF! | M90: =SUM(K90:L90) -> #REF!
B91: 2 | C91: 5 | D91: 0 | E91: F-5 Daş plitə döşəmə | J91: =SUM(J92:J94) -> #REF! | K91: =SUM(K92:K94) -> #REF! | L91: =SUM(L92:L94) -> #REF! | M91: =SUM(M92:M94) -> #REF!
B92: 2 | C92: 5 | D92: 1 | E92: Stone Travertino tile, 280 x 310 mm to 900 x 1320 mm x20 mm (Sadəcə işçilik üçün qiymət veiləcəkdir) | F92: m2 | G92: 437 | H92: ='1 - Direct_DK_BoQ'!#REF!*'0 - Summary'!$H$19 -> #REF! | I92: ='1 - Direct_DK_BoQ'!#REF!*'0 - Summary'!$G$15 -> #REF! | J92: =(H92+I92)*G92 -> #REF! | K92: =H92*G92 -> #REF! | L92: =I92*G92 -> #REF! | M92: =SUM(K92:L92) -> #REF!
B93: 2 | C93: 5 | D93: 2 | E93: Yapışdırıcı qat 5mm | F93: m2 | G93: 437 | H93: ='1 - Direct_DK_BoQ'!#REF!*'0 - Summary'!$H$19 -> #REF! | I93: ='1 - Direct_DK_BoQ'!#REF!*'0 - Summary'!$G$15 -> #REF! | J93: =(H93+I93)*G93 -> #REF! | K93: =H93*G93 -> #REF! | L93: =I93*G93 -> #REF! | M93: =SUM(K93:L93) -> #REF!
B94: 2 | C94: 5 | D94: 3 | E94: Metal torla gücləndirilmiş hamarlayıcı qat (qızdırıcı elementlərlə)-60mm | F94: m2 | G94: 437 | H94: ='1 - Direct_DK_BoQ'!#REF!*'0 - Summary'!$H$19 -> #REF! | I94: ='1 - Direct_DK_BoQ'!#REF!*'0 - Summary'!$G$15 -> #REF! | J94: =(H94+I94)*G94 -> #REF! | K94: =H94*G94 -> #REF! | L94: =I94*G94 -> #REF! | M94: =SUM(K94:L94) -> #REF!
B95: 2 | C95: 5 | D95: 4 | E95: XPS istilik izolyasiya qatı -50mm | F95: m2 | G95: 437 | H95: ='1 - Direct_DK_BoQ'!#REF!*'0 - Summary'!$H$19 -> #REF! | I95: ='1 - Direct_DK_BoQ'!#REF!*'0 - Summary'!$G$15 -> #REF! | J95: =(H95+I95)*G95 -> #REF! | K95: =H95*G95 -> #REF! | L95: =I95*G95 -> #REF! | M95: =SUM(K95:L95) -> #REF!
B96: 2 | C96: 5 | D96: 5 | E96: Hidroizolyasiya qatı | F96: m2 | G96: 437 | H96: ='1 - Direct_DK_BoQ'!#REF!*'0 - Summary'!$H$19 -> #REF! | I96: ='1 - Direct_DK_BoQ'!#REF!*'0 - Summary'!$G$15 -> #REF! | J96: =(H96+I96)*G96 -> #REF! | K96: =H96*G96 -> #REF! | L96: =I96*G96 -> #REF! | M96: =SUM(K96:L96) -> #REF!
B97: 2 | C97: 6 | D97: 0 | E97: F-9 döşəmə | J97: =SUM(J98:J100) -> #REF! | K97: =SUM(K98:K100) -> #REF! | L97: =SUM(L98:L100) -> #REF! | M97: =SUM(M98:M100) -> #REF!
B98: 2 | C98: 6 | D98: 1 | E98: Gym Flooring, PaviGym Performance, 900x0x5,5 mm (Sadəcə işçilik üçün qiymət veiləcəkdir) | F98: m2 | G98: 90 | H98: ='1 - Direct_DK_BoQ'!#REF!*'0 - Summary'!$H$19 -> #REF! | I98: ='1 - Direct_DK_BoQ'!#REF!*'0 - Summary'!$G$15 -> #REF! | J98: =(H98+I98)*G98 -> #REF! | K98: =H98*G98 -> #REF! | L98: =I98*G98 -> #REF! | M98: =SUM(K98:L98) -> #REF!
B99: 2 | C99: 6 | D99: 2 | E99: Zərbəqoruyucu döşəkçə - 15 mm | F99: m2 | G99: 90 | H99: ='1 - Direct_DK_BoQ'!#REF!*'0 - Summary'!$H$19 -> #REF! | I99: ='1 - Direct_DK_BoQ'!#REF!*'0 - Summary'!$G$15 -> #REF! | J99: =(H99+I99)*G99 -> #REF! | K99: =H99*G99 -> #REF! | L99: =I99*G99 -> #REF! | M99: =SUM(K99:L99) -> #REF!
B100: 2 | C100: 6 | D100: 3 | E100: Elastik poliuretan yapışqan - 7 mm | F100: m2 | G100: 90 | H100: ='1 - Direct_DK_BoQ'!#REF!*'0 - Summary'!$H$19 -> #REF! | I100: ='1 - Direct_DK_BoQ'!#REF!*'0 - Summary'!$G$15 -> #REF! | J100: =(H100+I100)*G100 -> #REF! | K100: =H100*G100 -> #REF! | L100: =I100*G100 -> #REF! | M100: =SUM(K100:L100) -> #REF!
B101: 2 | C101: 6 | D101: 4 | E101: Metal torla gücləndirilmiş hamarlayıcı qat (sement-qum məhlulu) - 91 mm | F101: m2 | G101: 90 | H101: ='1 - Direct_DK_BoQ'!#REF!*'0 - Summary'!$H$19 -> #REF! | I101: ='1 - Direct_DK_BoQ'!#REF!*'0 - Summary'!$G$15 -> #REF! | J101: =(H101+I101)*G101 -> #REF! | K101: =H101*G101 -> #REF! | L101: =I101*G101 -> #REF! | M101: =SUM(K101:L101) -> #REF!
...

Sheet 2 - Direct_MH_BoQ
B1: I HİSSƏ: ÖLÇÜLMÜŞ İŞLƏR / MEASURED WORKS
B2: Bənd | E2: Təsviri | F2: Vahid | G2: Miqdar | H2: Açıqlama | I2: Link vəya şəkil | J2: Müqavilə məbləği
J3: Vahid material qiyməti | K3: Vahid işçilik qiyməti | L3: Cəmi məbləğ
J4: AZN
B5: 1 | E5: Bu bölmədə əsas işlərin material və işçilik xərcləri orta bazar qiymətləri əsasında, balanslaşdırılmış şəkildə dəyərləndirilməlidir. Qiymətləndirmə zamanı material itkisi, sərfiyyat normaları və əmsallar, işlə bağlı tələb olunan köməkçi materiallar, materialların daşınması eləcə də gömrükləmə xərcləri nəzərə alınmalıdır. Bu işlərə dair üstəlik və dolayı xərclər, şirkətin mənfəəti vahid qiymətlərə daxil edilməməlidir və qiymət cədvəlinin I ci və II hissələrində öz əksini tapmalıdır. Burada qeyd edilmiş miqdarlar indikativ xarakter daşıyır. Həcmlərin hesablanmasında Sifarişçi tərəfindən təqdim edilən İşlərin Təsvirinə və Texniki Sənədlərə istinad edilməli və aşağıdakılarla məhdudlaşmayaraq İşlərə aid bütün detallar nəzərə alınmalıdır.
E6: Bakı şəhəri, Abşeron rayonu, Bilgəh qəsəbəsi, Zəfəran savxozu ərazisində yerləşən Fərdi yaşayış evi Əsas Bina və İtlər evində Memari işlər | J6: =SUMPRODUCT(J11:J28,$G$11:$G$28) -> 0 | K6: =SUMPRODUCT(K11:K28,$G$11:$G$28) -> 152508.24 | L6: =L7+#REF! -> #REF!
E7: Bakı şəhəri, Abşeron rayonu, Bilgəh qəsəbəsi, Zəfəran savxozu ərazisində yerləşən Fərdi yaşayış evi (Əsas Bina) Memarlıq və İnteryer işləri | L7: =#REF!+#REF!+#REF!+#REF!+#REF! -> #REF!
B8: 1 | E8: Bu bölmədə əsas işlərin material və işçilik xərcləri orta bazar qiymətləri əsasında, balanslaşdırılmış şəkildə dəyərləndirilməlidir. Qiymətləndirmə zamanı material itkisi, sərfiyyat normaları və əmsallar, işlə bağlı tələb olunan köməkçi materiallar, materialların daşınması eləcə də gömrükləmə xərcləri nəzərə alınmalıdır. Bu işlərə dair üstəlik və dolayı xərclər, şirkətin mənfəəti vahid qiymətlərə daxil edilməməlidir və qiymət cədvəlinin I ci və II hissələrində öz əksini tapmalıdır. Burada qeyd edilmiş miqdarlar indikativ xarakter daşıyır. Həcmlərin hesablanmasında Sifarişçi tərəfindən təqdim edilən İşlərin Təsvirinə və Texniki Sənədlərə istinad edilməli və aşağıdakılarla məhdudlaşmayaraq İşlərə aid bütün detallar nəzərə alınmalıdır.
E9: Ələt Azad İqtisadi Zonasında tikilməsi nəzərdə tutulan su anbarları, içməli və yağış suyu xətlərinin tikintisi Memarlıq işləri | L9: =SUM(L10,L14,L16,L19,L21,L24,L27) -> 178251.24
B10: 1 | C10: 1 | D10: 0 | E10: Keramik | L10: =SUM(L12:L14) -> 34003.6
B11: 1 | C11: 1 | D11: 1 | E11: Keramik plitələr | F11: m2 | G11: 210.6 | H11: (Yalnız işçilik qiymətləndiriləcəkdir) | K11: 25 | L11: =(J11+K11)*G11 -> 5265
B12: 1 | C12: 1 | D12: 2 | E12: Sement məhlulu ilə stəjka, qalınlığı 30 mm | F12: m2 | G12: 210.6 | H12: (Yalnız işçilik qiymətləndiriləcəkdir) | K12: 10 | L12: =(J12+K12)*G12 -> 2106
B13: 1 | C13: 1 | D13: 3 | E13: Keramik plintus (h=100 mm) | F13: m | G13: 111.2 | H13: (Yalnız işçilik qiymətləndiriləcəkdir) | K13: 8 | L13: =(J13+K13)*G13 -> 889.6
B14: 1 | C14: 2 | D14: 0 | E14: Epoksid | L14: =SUM(L15:L15) -> 31008
B15: 1 | C15: 2 | D15: 1 | E15: Su keçirməyən örtük (brend alternativləri və ya oxşar məhsullar: Sika Top Seal 107, BASF Ancronal 5442) | F15: m2 | G15: 3876 | H15: (Yalnız işçilik qiymətləndiriləcəkdir) | K15: 8 | L15: =(J15+K15)*G15 -> 31008
B16: 1 | C16: 3 | D16: 0 | E16: Qranit | L16: =SUM(L17:L18) -> 1341.8
B17: 1 | C17: 3 | D17: 1 | E17: Qumla fırçalanmış qranit üzlük, 600x400x20 m | F17: m2 | G17: 37 | H17: (Yalnız işçilik qiymətləndiriləcəkdir) | K17: 25 | L17: =(J17+K17)*G17 -> 925
B18: 1 | C18: 3 | D18: 2 | E18: Qranit plintus (h=100 mm) | F18: m | G18: 52.1 | H18: (Yalnız işçilik qiymətləndiriləcəkdir) | K18: 8 | L18: =(J18+K18)*G18 -> 416.8
B19: 1 | C19: 4 | D19: 0 | E19: Pilləkan qranit | L19: =SUM(L20:L20) -> 825
B20: 1 | C20: 4 | D20: 1 | E20: Giriş pilləkənləri, Qranit pillə üzlüyü (basamaq 30 mm, qaldırıcı 20 mm) | F20: ədəd | G20: 33 | H20: (Yalnız işçilik qiymətləndiriləcəkdir) | K20: 25 | L20: =(J20+K20)*G20 -> 825
B21: 1 | C21: 5 | D21: 0 | E21: TAVAN | L21: =SUM(L22:L23) -> 69629.84
B22: 1 | C22: 5 | D22: 1 | E22: Su keçirməyən örtük (brend alternativləri və ya oxşar məhsullar: Sika Top Seal 107, BASF Ancronal 5442), Sement-polimer hidroizolyasiya (Sika Top Seal 107 və ya ekv.) | F22: m2 | G22: 4508.4 | H22: (Yalnız işçilik qiymətləndiriləcəkdir) | K22: 15 | L22: =(J22+K22)*G22 -> 67626
B23: 1 | C23: =$C$21 -> 5 | D23: 2 | E23: Suya davamlı emulsiya boyası (rütubət üçün, RAL-9010, brend alternativləri və ya oxşar məhsullar: JOTUN, BETEK), | F23: m2 | G23: 250.48 | H23: (Yalnız işçilik qiymətləndiriləcəkdir) | K23: 8 | L23: =(J23+K23)*G23 -> 2003.84
B24: 1 | C24: 6 | D24: 0 | E24: DİVAR | L24: =SUM(L25:L26) -> 41223
B25: 1 | C25: =$C$24 -> 6 | D25: 1 | E25: Sement-polimer əsaslı iki komponentli su keçirməyən qoruyucu örtük (brend alternativləri və ya oxşar məhsullar: Sika Top Seal 107, BASF Ancronal 5442) | F25: m2 | G25: 2521 | H25: (Yalnız işçilik qiymətləndiriləcəkdir) | K25: 15 | L25: =(J25+K25)*G25 -> 37815
B26: 1 | C26: =$C$24 -> 6 | D26: =D25+1 -> 2 | E26: Suya davamlı emulsiya boyası (rütubət üçün, RAL-9010, brend alternativləri və ya oxşar məhsullar: JOTUN, BETEK) | F26: m2 | G26: 426 | H26: (Yalnız işçilik qiymətləndiriləcəkdir) | K26: 8 | L26: =(J26+K26)*G26 -> 3408
B27: 1 | C27: 7 | D27: 0 | E27: Qapılar | L27: =SUM(L28:L28) -> 220
B28: 1 | C28: =$C$27 -> 7 | D28: 1 | E28: Xarici yanğına davamlı qapı (boyalı RAL-7036, brend alternativləri və ya oxşar məhsullar: MKSmetal), Yanğına davamlı metal qapı EI120, 3200x3100 mm | F28: ədəd | G28: 2 | H28: (Yalnız işçilik qiymətləndiriləcəkdir) | K28: 110 | L28: =(J28+K28)*G28 -> 220

Sheet 3 - Indirect
A1: II HİSSƏ: İLKİN VƏ DOLAYI XƏRCLƏR / PRELİMİNARİES
A2: Bənd | B2: Təsviri | C2: Vahid | D2: Miqdar | E2: Müqavilə məbləği
E3: Vahid qiyməti | F3: Məbləğ
E4: AZN
A5: 2 | B5: Bu bölməyə layihə ilə bağlı üstəlik xərclər, o cümlədən administrativ xərclər, vergi və rüsum ödənişləri, əməyin təhlükəsizliyi ilə bağlı xərclər, baş ofisin xərcləri daxildir
A6: 2.1 | B6: Bütün ixtisaslı işçi heyətinin əmək haqları, Vizalar, İş icazələri, İşçilərə ödənilən kompensasiyalar, bonuslar və əmək məzuniyyəti (həmçinin xarici vətəndaşdırsa) və bunla bağlı olan səyahət xərcləri də daxil olan və bununla məhdudlaşmayan digər xərclər daxildir.
A7: 2.1.1 | B7: ___________ işləri üzrə Layihə Meneceri | C7: cəm | D7: 1 | E7: 48000 | F7: =D7*E7 -> 48000
A8: 2.1.2 | B8: ___________ işləri üzrə Menecer köməkçisi | C8: cəm | D8: 2 | E8: 30000 | F8: =D8*E8 -> 60000
A9: 2.1.3 | B9: Planlama üzrə Menecer | C9: cəm | D9: 1 | E9: 21600 | F9: =D9*E9 -> 21600
A10: 2.1.4 | B10: Layihələndirmə üzrə Menecer | C10: cəm | D10: 1 | E10: 42000 | F10: =D10*E10 -> 42000
A11: 2.1.5 | B11: İşçi layihələrin (Shopdrawings, As-built) hazırlanması üçün sahədə texniki komanda (İcraçı işlərin, təqdim edəcək bütün layihələndirmə məlumatlarının faktiki sahə ölçülərinə (as-built) uyğunlaşdırılmış olaraq dizayn etməli və faktiki ölçülər ilə fərqliliyə yol verməməlidir. Faktiki ölçülərdəki digər İcraçılara aid sapma və kənarlaşmalar norma və standartlar daxilində nəzərə alınmalıdır) | C11: cəm | D11: 4 | E11: 30000 | F11: =D11*E11 -> 120000
A12: 2.1.6 | B12: İşçi layihələrin (Shopdrawings) hazırlanması üçün sahə xaricində texniki komanda | C12: cəm | D12: 2 | E12: 2500 | F12: =D12*E12 -> 5000
A13: 2.1.7 | B13: Tikinti üzrə Menecer - ___________ işləri | C13: cəm | D13: 1 | E13: 1800 | F13: =D13*E13 -> 1800
A14: 2.1.8 | B14: Tikinti üzrə Menecer - ___________ işləri | C14: cəm | D14: 1 | E14: 1800 | F14: =D14*E14 -> 1800
A15: 2.1.9 | B15: Müvafiq sayda Nəzarətçi heyət (say qeyd edilməlidir) | C15: cəm | D15: 2 | E15: 2200 | F15: =D15*E15 -> 4400
A16: 2.1.10 | B16: Sınaq və İstismara vermə işləri – Mühəndis | C16: cəm | D16: 1 | E16: 2500 | F16: =D16*E16 -> 2500
A17: 2.1.11 | B17: Sınaq və İstismara vermə işləri – Mühəndis köməkçiləri | C17: cəm | D17: 1 | E17: 2500 | F17: =D17*E17 -> 2500
A18: 2.1.12 | B18: QA/QC - Menecer | C18: cəm | D18: 1 | E18: 36000 | F18: =D18*E18 -> 36000
... A25: 2.1.19 | B25: Digər nəzərdə tutulan işçilər | C25: cəm | D25: 1 | E25: 18000 | F25: =D25*E25 -> 18000
A26: 2.2 | B26: İşçi heyətinin yaşayış və məskunlaşma xərcləri | C26: cəm | D26: 50 | E26: 2880 | F26: =D26*E26 -> 144000
A27: 2.3 | B27: İşçi heyətinin bütün təhlükəsizlik, sağlamlıq və yaşayış qaydalarına riayət etməsi üçün bütün xərclər və haqlar. | C27: cəm | D27: 50 | E27: 540 | F27: =D27*E27 -> 27000
A28: 2.4 | B28: İşçi heyətinin fərdi mühafizə vasitələri ilə təmin edilməsi ilə bağlı bütün xərclər | C28: cəm | D28: 50 | E28: 250 | F28: =D28*E28 -> 12500
A29: 2.5 | B29: İşçi heyətinin sahəyə və oradan daşınması xərcləri | C29: cəm | D29: 50 | E29: 1800 | F29: =D29*E29 -> 90000
A30: 2.6 | B30: İşçi heyətinin yemək xərcləri | C30: cəm | D30: 50 | E30: 5400 | F30: =D30*E30 -> 270000
A31: 2.7 | B31: İşçi heyətinin mobilizasiyası | C31: cəm | D31: 50 | E31: 450 | F31: =D31*E31 -> 22500
A32: 2.8 | B32: İşçi heyətinin demobilizsiyası | C32: cəm | D32: 50 | E32: 450 | F32: =D32*E32 -> 22500
A33: 2.9 | B33: İcraçının sağlamlıq və əməyin təhlükəsizliyi və ətraf mühitin mühafizəsi və bununla bağlı zəruri tədbirlərin görülməsinə çəkilən xərclər | C33: cəm | D33: 50 | E33: 720 | F33: =D33*E33 -> 36000
A34: 2.1 | B34: Sahə təhlükəsizlik sistemlərinin təmin olunması | C34: cəm | D34: 50 | E34: 720 | F34: =D34*E34 -> 36000
A35: 2.11 | B35: Qanunvericiliklə nəzərdə tutulmuş bütün Vergilər, Rüsumlar, Bank xərcləri, bütün işçi heyətinin səhiyyə və pensiya ödənişi, sosial təminat haqları və s. | C35: cəm | D35: 50 | E35: 7128 | F35: =D35*E35 -> 356400
A36: 2.12 | B36: İcraçının özünə aid olan enerji təchizatı və işıq haqları, su təchizatı, içməli su və sərf materialları da daxil olmaqla ofis, düşərgə, ayaqyolu və digər müvəqqəti qurğuların istismarı və onlara texniki xidmət xərcləri | C36: cəm | D36: 10 | E36: 1800 | F36: =D36*E36 -> 18000
A37: 2.13 | B37: İcraçının özünü bütün mobil telefonlarla təmin etməsi və bütün xidmət haqları və aylıq hesabları öz hesabına ödəməsi | C37: cəm | D37: 10 | E37: 240 | F37: =D37*E37 -> 2400
A38: 2.14 | B38: Tikinti işlərinin planı, proqramı (qrafiki), işçi cizgilər, tikintidən əvvəlki vəziyyəti və işin gedişatını əks etdirən fotolar, faktiki icra cizgiləri, işin gedişatı, keyfiyyətə nəzarət, təhlükəsizliyə nəzarət, ətraf mühitə nəzarət üzrə hesabatların və digər sənədlərin hazırlanması və təqdim edilməsi | C38: cəm | F38: 90000
A39: 2.16 | B39: İcraçının bütün tələb edilən nümunələr, təcrübi modellər, prototiplər, sınaq və yoxlanışlar, əlaqədar sınaq verilənləri və sertifikatlarla Sifarişçiyə təqdim edilməsi | C39: cəm | F39: 50000
A40: CƏM: | F40: =SUM(F5:F39) -> 1609500

Sheet 4 - Overhead
A1: III HİSSƏ: ÜSTƏLİK XƏRCLƏR / OVERHEAD
A2: Bənd | B2: Təsviri | C2: Vahid | D2: Miqdar | E2: Müqavilə məbləği
E3: Vahid qiyməti | F3: Məbləğ
E4: AZN
A5: 1 | B5: Bu bölməyə layihə ilə bağlı ilkin və dolayı xərclər və eləcə də mobilizasiya və demobilizasiya işləri və onların dəyərləndirilməsi daxildir.
A6: 1.1 | B6: Zəmanət və Sığorta
A7: 1.1.1 | B7: İcra zəmanətinin təmin edilməsi 5% | C7: cəm | F7: =D7*E7 -> 0
A8: 1.1.2 | B8: Avans zəmanətinin təmin edilməsi | C8: cəm | F8: =D8*E8 -> 0
A9: 1.1.3 | B9: İşəgötürənin məsuliyyət sığortası, maşın mexanizm, texnika və avadanlıqların icbari sığortası, üçüncü şəxsələr qarşısında məsuliyyət sığortası | C9: cəm | F9: 12000
A10: 1.2 | B10: Mobilizasiya xərcləri | F10: =D10*E10 -> 0
A11: 1.2.1 | B11: Layihənin icrası üçün lazım olan Sahə ofisi və texniki işçilərin işə cəlb edilməsi xərcləri, ofis və ambar konteynerləri, kompyuter, printer, skaner, plotter vasitələri və işin icrası üçün tələb olunan software proqramları, mebel, dəftərxana, avadanlıqları, internet, telefon və s. xərclər, avtonəqliyat vasitələri, yoxlama, nəzarət, hazırlıq işləri üçün alət və avadanlıqlar (məsələn test avadanlığı, total station, nivelir və s.) məişət avadanlıqları və kondisionerlər, köməkçi vasitələr və s. daxildir. | C11: cəm | F11: 45000
A12: 1.2.2 | B12: Müvəqqəti meydança (ərazi), hasar, barrikada, siqnal lampası, işıqlandırma, xəbərdarlıq işarələri, plakatlar, müvəqqəti tutacaqlar, baryerlər, kənar müdafiə, lövhələr və hər növ təhlükəsizlik ilə əlaqədar önləyici tədbirlərin nəzərə alınması xərcləri | C12: cəm | F12: 38000
A13: 1.3 | B13: Avadanlıqların, Qurğuların, Maşın və Mexanizmlərin və s. təmin olunması | F13: =D13*E13 -> 0
A14: 1.5.1 | B14: İşlərin yerinə yetirilməsi üçün lazım olan bütün qurğuların, avadanlıqların, maşın və texnikaların, əl alətlərinin təmin edilməsi xərcləri | C14: cəm | F14: 722000
A15: 1.3.2 | B15: Taxtabəndlərin (ayaqaltıların) quraşdırılması və çıxarılması daxil olmaqla İşlərin vaxtında həyata keçirilməsi və tamamlanması üçün zəruri olan bütün müvəqqəti taxtabənd və aksessuarlarla təmin edilməsi xərcləri. | C15: cəm | D15: 60 | E15: 390 | F15: =D15*E15 -> 23400
A16: 1.5.3 | B16: Şaquli və üfüqi daşımalar (müvəqqəti lift, servis yükləmə platforması və s.), qaldırıcı meydançalar, asma meydançaları, nəqliyyat vasitələri, vasitələr və xidmətlər daxil olmaqla bütün inşaat ləvazimatlarıyla təmin etmək. Ləvazimatlara qoruyucu geyim və təhlükəsizlik avadanlığı da daxil edilir. | C16: cəm | F16: 65000
A17: 1.6 | B17: Müvəqqəti İşlər | F17: =D17*E17 -> 0
A18: 1.6.1 | B18: Müvəqqəti meydança (ərazi), yol və binalar | C18: cəm | F18: 35000
A19: 1.6.5 | B19: İcraçının özünün məişət obyektləri ilə (icraçının ofisi, istehsalat bazası, düşərgə, ayaqyolu, laboratoriya, anbar və digər tikililərin) təmin etməsi | C19: cəm | F19: 25000
A20: CƏM: | F20: =SUM(F5:F19) -> 965400

Sheet Scope_Matrix
B2: RESPONSIBILITY MATRIX FOR ARCHITECTURE WORKS/MEMARLIQ İŞLƏRİ ÜÇÜN TƏRƏFLƏRİN MƏSULİYYƏT CƏDVƏLİ
B4: ITEM NO | C4: İŞLƏRİN TƏSVİRİ | D4: DESCRIPTION | E4: Supplied By/ Təchiz edən | G4: Paid By/ Ödəyən | I4: REMARKS/QEYDLƏR
E5: CON | F5: SUBCON | G5: CON | H5: SUBCON
B6: 1 | C6: ƏSAS İŞÇİ HEYƏTİ | D6: DIRECT WORKMANSHIP
B7: 1.1 | C7: Əmək haqqı xərcləri | D7: Wage Expenses | F7: X | H7: X
B8: 1.2 | C8: Beynəlxalq nəqliyyat xərcləri | D8: International Transportation Expenses | F8: X | H8: X
B9: 1.3 | C9: Azərbaycan daxili nəqliyyat xərcləri | D9: Transportation Expenses Inside Azerbaijan | F9: X | H9: X
B10: 1.4 | C10: Qidalanma xərcləri (3 yemək) | D10: Food Expenses (3 meal) | F10: X | H10: X
B11: 1.5 | C11: İşçilərin Yerləşim Xərcləri | D11: Accommodation Expenses | F11: X | H11: X
B12: 1.6 | C12: İş Forması/Geyim | D12: Working Uniform/Dress | F12: X | H12: X
B13: 1.7 | C13: İşçilərin Nəqliyyatı | D13: Local Transportation | F13: X | H13: X
B14: 1.8 | C14: Sosial Təminat & Tibbi Xərclər | D14: Social Security & Medical Expenses | F14: X | H14: X
B15: 1.9 | C15: Viza Qeydiyyatı Xərcləri | D15: Visa Registration Expenses | F15: X | H15: X
B16: 1.10 | C16: Karantina Xərcləri (Əmək haqqı və. s) | D16: Quarantine Expenses (Wage and Other) | F16: X | H16: X
B17: 2 | C17: DİGƏR İŞÇİ HEYƏTLƏRİ | D17: INDIRECT PERSONNEL
B18: 2.1 | C18: Əmək haqqı xərcləri | D18: Wage Expenses | F18: X | H18: X
B19: 2.2 | C19: Beynəlxalq nəqliyyat xərcləri | D19: International Transportation Expenses | F19: X | H19: X
B20: 2.3 | C20: Azərbaycan daxili nəqliyyat xərcləri | D20: Transportation Expenses Inside Azerbaijan | F20: X | H20: X
B21: 2.4 | C21: Qidalanma xərcləri | D21: Food Expenses (3 meal) | F21: X | H21: X
B22: 2.5 | C22: İşçilərin Yerləşim Xərcləri | D22: Accommodation Expenses | F22: X | H22: X
B23: 2.6 | C23: İş Forması/Geyimi | D23: Working Uniform/Dress | F23: X | H23: X
B24: 2.7 | C24: İşçilərin Nəqliyyatı | D24: Local Transportation | F24: X | H24: X
B25: 2.8 | C25: Sosial Təminat & Tibbi Xərclər | D25: Social Security & Medical Expenses | F25: X | H25: X
B26: 2.9 | C26: Viza Qeydiyyatı Xərcləri | D26: Visa Registration Expenses | F26: X | H26: X
B27: 2.10 | C27: Karantina Xərcləri (Əmək haqqı və. s) | D27: Quarantine Expenses (Wage and Other) | F27: X | H27: X
B28: 3 | C28: TİKİNTİ SAHƏSİNİN XƏRCLƏRİ | D28: SITE OVERHEADS
B29: 3.1 | C29: Mobilizasiya xərcləri | D29: Mobilization Cost | F29: X | H29: X
B30: 3.2 | C30: Sahə ofisləri | D30: Site Offices | F30: X | H30: X
B31: 3.3 | C31: Alətlər və tikinti materialları üçün anbar | D31: Warehouse for Handtools and Consumables | F31: X | H31: X
B32: 3.4 | C32: Müvəqqəti su və Kanalizasiya | D32: Temporary water and waste water | F32: X | H32: X
B33: 3.5 | C33: Elektrik mənbəyinin təmin edilməsi | D33: Prodiving electrical power point | E33: X | G33: X
B34: 3.6 | C34: Elektrik xərcləri | D34: Electricity Costs | E34: X | G34: X
B35: 3.7 | C35: İşıqlandırma xərcləri | D35: Lighting Costs | F35: X | H35: X
B36: 3.8 | C36: Elektrik kabelləri | D36: Electrical cables from power point | F36: X | H36: X
B37: 3.9 | C37: Zibillərin yığılması və Tikinti sahəsinin təmizliyi | D37: Garbage removal & Site Cleaning | F37: X | H37: X
B38: 3.10 | C38: Qar təmizliyi | D38: Snow Removing | F38: X | H38: X
B39: 3.11 | C39: Ofis komputerləri, avadanlıqlar və mebellər | D39: Office Computers, Devices and Furniture | F39: X | H39: X
B40: 3.12 | C40: Ofis internet xərcləri | D40: Office internet expenses | F40: X | H40: X
B41: 3.13 | C41: Mobil telefon | D41: Mobile phones | F41: X | H41: X
B42: 3.14 | C42: Stasionar | D42: Stationary | F42: X | H42: X
B43: 4 | C43: LAYİHƏ MATERİALLARI | D43: PROJECT MATERIAL
B44: 4.1 | C44: Layihədə istifadə olunacaq material | D44: Project Material | F44: X | H44: X
B45: 4.2 | C45: Layihə materialının təsdiqi | D45: Approval of project material | E45: X | G45: X
B46: 5 | C46: ALƏT VƏ İSTİFADƏ OLUNAN MATERİALLAR | D46: TOOLS & CONSUMABLES
B47: 5.1 | C47: Əl alətləri və tikinti materialları | D47: Handtools & Consumables | F47: X | H47: X
B48: 5.2 | C48: Tal,yükqaldıran avadanlıq və zəncirlərin təmin olunması | D48: Slings & Shackle | F48: X | H48: X
B49: 5.3 | C49: Bütün müvəqqəti materiallar | D49: All Temporary Materials | F49: X | H49: X
B50: 5.4 | C50: Sətəm üçün istehsal materialları | D50: HSE Consumables | F50: X | H50: X
B51: 6 | C51: SERTİFİKATLAR VƏ TESTLƏR | D51: CERTIFICATES AND TESTS
B52: 6.1 | C52: Fəaliyyət növünə görə icazə sənədləri | D52: Permitting documents by type of activity | F52: X | H52: X
B53: 6.2 | C53: Yüksəkdə işləmək | D53: Working at height | F53: X | H53: X
B54: 6.3 | C54: Səbətlərdə işləmək | D54: Working at cradles | F54: X | H54: X
B55: 6.4 | C55: Yanğın zamanı təhlükəsizlik qaydaları | D55: Fire-technical minimum (PTM) | F55: X | H55: X
B56: 6.5 | C56: NAKS Sertifikatı (Ümumi) | D56: NAKS Certificates (General) | F56: X | H56: X
B57: 6.6 | C57: Qaynaqçı sertiftikatı (layihəyə bağlı) | D57: Welder Certificates (Particular for Project) | F57: X | H57: X
B58: 6.7 | C58: Azərbaycan qanunvericiliyinə uyğun olaraq tələb olunan digər icazələr | D58: Other permits required under Azerbaijan law | F58: X | H58: X
B59: 6.8 | C59: Armatur testləri | D59: Reinforcement tests | F59: X | H59: X
B60: 6.9 | C60: Beton testləri | D60: Concrete tests | F60: X | H60: X
B61: 6.10 | C61: Qaynaq testləri | D61: Welding test | F61: X | H61: X
B62: 6.11 | C62: İcraat prosesi (PPR və Texniki sədənlərin hazırlanması) | D62: Method of Statement (Preparation of PPR, TechCard etc.) | F62: X | H62: X
B63: 7 | C63: İNŞAAT TEXNİKASI VƏ AVADANLIQLAR | D63: CONSTRUCTION EQUIPMENT & MACHINERY
B64: 7.1 | C64: Texnika və avadanlıqlar | D64: Machinery & Equipment | F64: X | H64: X
B65: 7.2 | C65: Manipulyator | D65: Hi-up | F65: X | H65: X
B66: 7.3 | C66: Avtokran | D66: Autocrane | F66: X | H66: X
B67: 7.4 | C67: Avtosəbət | D67: Aerial platform | F67: X | H67: X
B68: 7.5 | C68: İnyeksiya üçün nasos və digər avadanlıqlar | D68: Injection pump and other equipment | F68: X | H68: X
B69: 8 | C69: MALLİYƏ XƏRCLƏR VƏ VERGİ | D69: FINANCIAL EXPENSES & TAX
B70: 8.1 | C70: İşçilərin vergisi, Sosial sığörta xidmətləri | D70: Personnel Tax and Social Insurance | F70: X | H70: X
B71: 8.2 | C71: Gəlir vergisi | D71: Income Tax | F71: X | H71: X
B72: 8.3 | C72: Bank komissiya xidmətləri | D72: Bank Comissions | F72: X | H72: X
B73: 8.4 | C73: İcra Zəmanəti | D73: Performans Bond | F73: X | H73: X
B74: 8.5 | C74: Avans Zəmanəti | D74: Advance Payment Bond | F74: X | H74: X
B75: 8.6 | C75: Bütün risklərin sığörtalanması | D75: All Risk Insurance | F75: X | H75: X
B76: 8.7 | C76: Gözlənilməz xərclər | D76: Unforseen expenses | F76: X | H76: X
B77: 8.8 | C77: Ümumi xərclər | D77: General HQ Expenses | F77: X | H77: X
B78: 9 | C78: ƏRAZİDƏ OLAN İŞLƏR | D78: SITE ACTIVITIES
B79: 9.1 | C79: Texniki Sorğu, Materialın Təsdiq Forması | D79: Technical Query, Material Aproval Form | F79: X | H79: X
B80: 9.2 | C80: İcraat prosesinin hazırlanması | D80: Preparation of Method Statements | F80: X | H80: X
B81: 9.3 | C81: Təhvil təslim aktlarının hazırlanması | D81: Preparing Act and Handover Documents | F81: X | H81: X
B82: 9.4 | C82: Akt və digər Sənədlər üçün Hüquqi Təsdiqlərin Təmin edilməsi | D82: Providing Legal Approvals for Act and other Documents | F82: X | H82: X
B83: 9.5 | C83: Səlahiyyətli şəxslərə təhvil verilməsi | D83: Handing over to authorities | F83: X | H83: X
B84: 9.6 | C84: İşçi layihələr | D84: Construction Drawings | E84: X | G84: X
B85: 9.7 | C85: Shop drawings | D85: Shop drawings | F85: X | H85: X
B86: 9.8 | C86: As-built cizgilər | D86: As-built Drawings | F86: X | H86: X
B87: 9.9 | C87: Lazımi bütün keyfiyyət kontrol sənədləri | D87: All necessary quality control documentation | F87: X | H87: X
B88: 9.10 | C88: Günlük raportların AZCD- ə verilməsi | D88: Daily Report according to AZCD reports | F88: X | H88: X
B89: 9.11 | C89: Həftəlik raportların AZCD- ə verilməsi | D89: Weekly Report | F89: X | H89: X
B90: 9.12 | C90: Bütün Personel CV-nin təmin edilməsi | D90: Providing the All Indirect Personnel CV | F90: X | H90: X
B91: 9.13 | C91: İşlərin irəlilləmə raportu | D91: Progress Update | F91: X | H91: X
B92: 9.14 | C92: Gələn yoxlamalar | D92: Incoming Inspection | E92: X | F92: X | G92: X | H92: X
B93: 9.15 | C93: Scaffoldlarin tamin olunmasi qurasdirilmasi | D93: Scaffolding material and scaffolding installation | F93: X | H93: X
B94: 9.16 | C94: AZDTN standartlarına uyğun olaraq bütün tələb olunan testlər | D94: All the required test according to AZDTN standards | F94: X | H94: X
B95: 9.17 | C95: Topoqraf işləri | D95: Surveying Works | F95: X | H95: X
B96: 9.18 | C96: Qapalı sahələrdə işləyən işçilər üçün müvəqqəti havalandırma üçün ventilyatorların (fanların) və havalandırma kanallarının təmini və quraşdırılması | D96: Supply and installation of ventilators (fans) and ventilation ducts for temporary ventilation for workers working in enclosed areas | F96: X | H96: X
B97: 9.19 | C97: Qapalı sahələrdə işləyən işçilər üçün müvəqqəti işıqlandırmanın və elektrik xəttinin çəkilməsi | D97: Installation of temporary lighting and power lines for workers working in confined spaces | F97: X | H97: X
B98: 9.20 | C98: Bütün artıq layihə materialları müvafiq sənədlərlə birlikdə Podratçıya təhvil veriləcək | D98: All surplus project materials will be handed over to Contractor with proper documentation | F98: X | H98: X
B99: 9.21 | C99: Qış şəraitində işlərin görülməsi | D99: Winterization | F99: X | H99: X
B100: 9.22 | C100: Horizontal və Vertiqal daşınmalar | D100: All horizontal and vertical transportation | F100: X | H100: X
B101: 9.23 | C101: Materialın əraziyə çatdırılması və qorunması | D101: Protection of the material until delivery of the material | F101: X | H101: X
B102: 9.24 | C102: Sahədə cavabdeh şəxlərin olması | D102: Having responsible individuals on the site. | F102: X | H102: X
...

Sheet Org_chart
G5: PROJECT ORGANIZATIONAL CHART / LAYİHƏNİN İDARƏETMƏ STRUKTURU
Y7: Layihə üzrə idarəetmə və mühəndis-texniki heyət
Y9: № | Z9: Vəzifə | AA9: Say
A10: LAYİHƏ RƏHBƏRİ / LAYİHƏ MENECERİ | Y10: 1 | Z10: Layihə Meneceri | AA10: 1
A11: │ | Y11: 2 | Z11: Layihə Menecerinin köməkçisi | AA11: 2
A12: ┌────────────────────────┼────────────────────────┐ | Y12: 3 | Z12: Planlama üzrə Menecer | AA12: 1
A13: │ │ │ | Y13: 4 | Z13: Layihələndirmə üzrə Menecer | AA13: 1
A14: ▼ ▼ ▼ | Y14: 5 | Z14: Shopdrawing / As-built üzrə texniki heyət | AA14: 4
A15: MENECER KÖMƏKÇİLƏRİ PLANLAMA MENECERİ LAYİHƏLƏNDİRMƏ | Y15: 6 | Z15: Sahə xarici texniki layihələndirmə heyəti | AA15: 2
A16: 2 nəfər 1 nəfər MENECERİ | Y16: 7 | Z16: Dəmir-beton işləri üzrə Tikinti Meneceri | AA16: 1
A17: │ | Y17: 8 | Z17: Ümumi tikinti işləri üzrə Tikinti Meneceri | AA17: 1
A18: ▼ | Y18: 9 | Z18: Nəzarətçi | AA18: 2
A19: SHOPDRAWING / AS-BUILT | Y19: 10 | Z19: Sınaq və istismara vermə mühəndisi | AA19: 1
A20: TEXNİKİ KOMANDA | Y20: 11 | Z20: Sınaq və istismara vermə mühəndisinin köməkçisi | AA20: 1
A21: 4 nəfər | Y21: 12 | Z21: QA/QC Meneceri | AA21: 1
... A28: │ ┌──────┼──────┐ │ | Y28: 19 | Z28: Digər texniki və inzibati heyət | AA28: 1
A29: │ │ │ │ ▼
A30: │ ▼ ▼ ▼ SƏTƏM KÖMƏKÇİSİ | Y30: Qeyd: Layihənin iş həcminə və iş qrafikinə uyğun olaraq fəhlə heyətinin sayı və tərkibi işlərin intensivliyinə əsasən dəyişdirilə bilər.
A31: │ QA/QC QA/QC SINAQ 1 nəfər
A32: │ ELEKTRİK MEXANİK VƏ
A33: │ MÜH. MÜH. İSTİSMAR
A34: │ MÜH.
A35: │
A36: ├───────────────┬───────────────┐
A37: ▼ ▼ ▼
A38: ARMATUR İŞLƏRİ QƏLİB İŞLƏRİ BETON İŞLƏRİ
A39: │ │ │
A40: └───────────────┼───────────────┘
A41: ▼
A42: SAHƏ İCRA HEYƏTİ
... A51: İŞÇİLƏRİ
B57: 2. BAŞ OFİSİN LAYİHƏ ÜZRƏ İDARƏETMƏ VƏ FUNKSİONAL DƏSTƏK STRUKTURU
C62: ISCG MMC – BAŞ OFİS | Z62: Baş Ofisin layihə üzrə funksiyaları
C63: │
C64: ▼ | Z64: Baş Ofis funksiyası | AA64: Layihəyə göstərilən dəstək
C65: BAŞ DİREKTOR | Z65: Baş Direktor | AA65: Layihənin ümumi strateji və inzibati idarə edilməsi, əsas qərarların qəbul edilməsi
C66: │ | Z66: Texniki Direktorluq / Baş Mühəndis | AA66: Texniki məsələlərə, metodologiyaya və layihə həllərinə dəstək
C67: ┌───────────────┬────────┼────────┬───────────────┐ | Z67: Kommersiya / Tender Şöbəsi | AA67: Müqavilə, kommersiya məsələləri, dəyişikliklər və yazışmalar
C68: │ │ │ │ │ | Z68: Maliyyə və Mühasibatlıq | AA68: Büdcə, ödənişlər, əməkhaqqı, maliyyə hesabatları və vergi məsələləri
C69: ▼ ▼ ▼ ▼ ▼ | Z69: Satınalma və Təchizat | AA69: Beton, armatur, qəlib materialları, XPS, hidroizolyasiya və digər materialların satın alınması
C70: TEXNİKİ KOMMERSİYA MALİYYƏ SATINALMA HÜQUQ | Z70: Logistika | AA70: Material, avadanlıq və işçi heyətinin sahəyə çatdırılmasının koordinasiyası
C71: DİREKTORLUQ / TENDER VƏ VƏ TƏCHİZAT ŞÖBƏSİ | Z71: Hüquq Şöbəsi | AA71: Müqavilələr, hüquqi yazışmalar, iddialar və müqavilə öhdəliklərinin hüquqi təminatı
C72: │ ŞÖBƏSİ MÜHASİBAT │ | Z72: HR | AA72: İşçilərin seçilməsi, əmək müqavilələri, şəxsi işlər, əməkhaqqı və kadr təminatı
C73: │ │ | Z73: QA/QC | AA73: Keyfiyyət sisteminə metodoloji dəstək, prosedurlar və texniki sənədlərin yoxlanılması
C74: ├── Baş mühəndis ├── Material | Z74: SƏTƏM | AA74: Əməyin təhlükəsizliyi, sağlamlıq və ətraf mühit üzrə sahəyə metodoloji nəzarət
C75: ├── QA/QC ├── Avadanlıq | Z75: Sənədləşmə / Arxiv | AA75: Layihə sənədlərinin, hesabatların və müqavilə sənədlərinin idarə olunması
C76: ├── Layihələndirmə └── Logistika
C77: └── Texniki dəstək
C78: │
C79: └──────────────────────┐
C80: │
C81: ▼
C82: LAYİHƏ MENECERİ
C83: İLƏ KOORDİNASİYA
C84: │
C85: ┌────────────────┼────────────────┐
C86: │ │ │
C87: ▼ ▼ ▼
... C90: TƏHLÜKƏSİZLİK

Sheet Planning
B2: Work Schedule / İş cədvəli
B3: Description of Work / İşin təsviri | C3: Start / Başlanğıc | D3: Finish / Bitmə tarixi | E3: Duration / Müddət
B4: Metal ve Demir beton konstruksiya işləri | E4: 360
A8: № | B8: İşlərin adı | C8: Başlanğıc | D8: Bitmə | E8: Müddət
A9: 1 | B9: Mobilizasiya və sahənin təşkili | C9: 1-ci gün | D9: 10-cu gün | E9: 10 gün
A10: 2 | B10: Topoqrafik ölçmə və nişanlama işləri | C10: 1-ci gün | D10: 10-cu gün | E10: 10 gün
A11: 3 | B11: Qazıntı işləri | C11: 5-ci gün | D11: 45-ci gün | E11: 41 gün
A12: 4 | B12: Qazılmış torpağın daşınması/utilizasiyası | C12: 10-cu gün | D12: 45-ci gün | E12: 36 gün
A13: 5 | B13: Mexaniki sıxlaşdırma | C13: 25-ci gün | D13: 50-ci gün | E13: 26 gün
A14: 6 | B14: Çınqıl/qırmadaşla dolğu və sıxlaşdırma | C14: 45-ci gün | D14: 60-cı gün | E14: 16 gün
A15: 7 | B15: Geri doldurma işləri | C15: 50-ci gün | D15: 70-ci gün | E15: 21 gün
A16: 8 | B16: Polietilen plyonkanın sərilməsi | C16: 55-ci gün | D16: 65-ci gün | E16: 11 gün
A17: 9 | B17: B7.5 hazırlıq betonunun tökülməsi | C17: 60-cı gün | D17: 75-ci gün | E17: 16 gün
A18: 10 | B18: Hidroizolyasiya işləri | C18: 70-ci gün | D18: 100-cü gün | E18: 31 gün
A19: 11 | B19: XPS və drenaj lövhələrinin quraşdırılması | C19: 90-cı gün | D19: 115-ci gün | E19: 26 gün
A20: 12 | B20: Tava bünövrə – armatur işləri | C20: 70-ci gün | D20: 110-cu gün | E20: 41 gün
... A36: 28 | B36: Yekun təhvil və demobilizasiya | C36: 295-ci gün | D36: 300-cü gün | E36: 6 gün
B38: Ehtiyat/rezerv müddəti | C38: 60 gün
